{"id":"050764","title":"台川","author":"宮沢賢治","authorId":"000081","blocks":[{"k":"p","r":[{"t":"〔もうでかけましょう。〕たしかに光がうごいてみんな立ちあがる。"},{"b":"腰","f":"こし"},{"t":"をおろしたみじかい草。かげろうか何かゆれている。かげろうじゃない。"},{"b":"網膜","f":"もうまく"},{"t":"が"},{"b":"感","f":"かん"},{"t":"じただけのその光だ。"}]},{"k":"p","r":[{"t":"〔さあでかけましょう。行きたい人だけ。〕まだ来ないものは"},{"b":"仕方","f":"しかた"},{"t":"ない。さっきからもう二十分も"},{"b":"待","f":"ま"},{"t":"ったんだ。もっともこのみちばたの青いいろの"},{"b":"寄宿舎","f":"きしゅくしゃ"},{"t":"はゆっくりして"},{"b":"爽","f":"さわや"},{"t":"かでよかったが。"}]},{"k":"p","r":[{"t":"これからまたここへ"},{"b":"一遍","f":"いっぺん"},{"t":"帰って十一時には"},{"b":"向","f":"むこ"},{"t":"うの"},{"b":"宿","f":"やど"},{"t":"へつかなければいけないんだ。「"},{"b":"何処","f":"どご"},{"t":"さ行ぐのす。」そうだ、"},{"b":"釜淵","f":"かまぶち"},{"t":"まで行くというのを知らないものもあるんだな。〔釜淵まで、"},{"b":"一寸","f":"ちょっと"},{"t":"三十分ばかり。〕"}]},{"k":"p","r":[{"t":"おとなしい新らしい白、"},{"b":"緑","f":"みどり"},{"t":"の中だから、そして外光の中だから大へんいいんだ。"},{"b":"天竺木綿","f":"てんじくもめん"},{"t":"、その"},{"b":"菓子","f":"かし"},{"t":"の"},{"b":"包","f":"つつ"},{"t":"みは"},{"b":"置","f":"お"},{"t":"いて行ってもいい。"},{"b":"雑嚢","f":"ざつのう"},{"t":"や何かもここの"},{"b":"芝","f":"しば"},{"t":"へおろしておいていい行かないものもあるだろうから。"}]},{"k":"p","r":[{"t":"「私はここで待ってますから。」校長だ。校長は"},{"b":"肥","f":"ふと"},{"t":"ってまっ黒にいで立ちたしかにゆっくりみちばたの草、林の前に足を"},{"b":"開","f":"ひら"},{"t":"いて"},{"b":"投","f":"な"},{"t":"げ出している。"}]},{"k":"p","r":[{"t":"〔はあ、では一寸行って"},{"b":"参","f":"まい"},{"t":"ります。〕木の青、木の青、空の雲は今日も"},{"b":"甘酸","f":"あまず"},{"t":"っぱく、足なみのゆれと光の"},{"b":"波","f":"なみ"},{"t":"。足なみのゆれと光の波。"}]},{"k":"p","r":[{"b":"粘土","f":"ねんど"},{"t":"のみちだ。"},{"b":"乾","f":"かわ"},{"t":"いている。黄色だ。みち。粘土。"}]},{"k":"p","r":[{"b":"小松","f":"こまつ"},{"t":"と林。林の"},{"b":"明暗","f":"めいあん"},{"t":"いろいろの緑。それに"},{"b":"生徒","f":"せいと"},{"t":"はみんな"},{"b":"新鮮","f":"しんせん"},{"t":"だ。"}]},{"k":"p","r":[{"t":"そしてそうだ、向うの"},{"b":"崖","f":"がけ"},{"t":"の黒いのはあれだ、明らかにあの"},{"b":"黒曜石","f":"こくようせき"},{"t":"の dyke だ。ここからこんなにはっきり見えるとは思わなかったぞ。"}]},{"k":"p","r":[{"t":"よしうまい。"}]},{"k":"p","r":[{"t":"〔"},{"b":"向","f":"むこ"},{"t":"うの"},{"b":"崖","f":"がけ"},{"t":"をごらんなさい。黒くて少し"},{"b":"浮","f":"う"},{"t":"き出した"},{"b":"柱","f":"はしら"},{"t":"のような岩があるでしょう。あれは"},{"b":"水成岩","f":"すいせいがん"},{"t":"の"},{"b":"割","f":"わ"},{"t":"れ目に"},{"b":"押","f":"お"},{"t":"し"},{"b":"込","f":"こ"},{"t":"んで来た火山岩です。黒曜石です。〕ダイクと"},{"b":"云","f":"い"},{"t":"おうかな。いいや"},{"b":"岩脈","f":"がんみゃく"},{"t":"がいい。〔ああいうのを岩脈といいます。〕わかったかな。"}]},{"k":"p","r":[{"t":"〔わかりましたか。向うの崖に黒い岩が"},{"b":"縦","f":"たて"},{"t":"に"},{"b":"突","f":"つ"},{"t":"き出ているでしょう。"}]},{"k":"p","r":[{"t":"あれは水成岩のなかにふき出した火成岩ですよ。岩脈ですよ。あれは。〕"}]},{"k":"p","r":[{"t":"ゆれてるゆれてる。光の"},{"b":"網","f":"あみ"},{"t":"。"}]},{"k":"p","r":[{"t":"〔この山は"},{"b":"流紋凝灰岩","f":"りゅうもんぎょうかいがん"},{"t":"でできています。"},{"b":"石英粗面岩","f":"せきえいそめんがん"},{"t":"の凝灰岩、大へん"},{"b":"地味","f":"ちみ"},{"t":"が"},{"b":"悪","f":"わる"},{"t":"いのです。"},{"b":"赤松","f":"あかまつ"},{"t":"とちいさな"},{"b":"雑木","f":"ぞうき"},{"t":"しか"},{"b":"生","f":"は"},{"t":"えていないでしょう。ところがそのへん、"},{"b":"麓","f":"ふもと"},{"t":"の"},{"b":"緩","f":"ゆる"},{"t":"い"},{"b":"傾斜","f":"けいしゃ"},{"t":"のところには青い"},{"b":"立派","f":"りっぱ"},{"t":"な"},{"b":"闊葉樹","f":"かつようじゅ"},{"t":"が"},{"b":"一杯","f":"いっぱい"},{"b":"生","f":"は"},{"t":"えているでしょう。あすこは古い"},{"b":"沖積扇","f":"ちゅうせきせん"},{"t":"です。"},{"b":"運","f":"はこ"},{"t":"ばれてきたのです。"},{"b":"割合","f":"わりあい"},{"b":"肥沃","f":"ひよく"},{"t":"な"},{"b":"土壌","f":"どじょう"},{"t":"を作っています。木の生え"},{"b":"工合","f":"ぐあい"},{"t":"がちがって見えましょう。わかりましょう。〕わかるだろうさ。けれどもみんな"},{"b":"黙","f":"だま"},{"t":"って歩いている。これがいつでもこうなんだ。さびしいんだ。けれども何でもないんだ。"}]},{"k":"p","r":[{"b":"後","f":"うし"},{"t":"ろで"},{"b":"誰","f":"だれ"},{"t":"かこごんで石ころを"},{"b":"拾","f":"ひろ"},{"t":"っているものもある。小松ばやしだ。"},{"b":"混","f":"こ"},{"t":"んでいる。このみちはずうっと"},{"b":"上流","f":"じょうりゅう"},{"t":"まで通っているんだ。"},{"b":"造林","f":"ぞうりん"},{"t":"のときは"},{"b":"苗","f":"なえ"},{"t":"や何かを一杯つけた馬がぞろぞろここを行くんだぞ。"}]},{"k":"p","r":[{"t":"〔"},{"b":"志戸平","f":"しどたいら"},{"t":"のちかく"},{"b":"豊沢","f":"とよさわ"},{"t":"川の南の方に"},{"b":"杉","f":"すぎ"},{"t":"のよくついた"},{"b":"奇麗","f":"きれい"},{"t":"な山があるでしょう。あすことこことはとても木の生え工合や"},{"b":"較","f":"くら"},{"t":"べにも何にもならないでしょう。"},{"b":"向","f":"むこ"},{"t":"うは"},{"b":"安山岩","f":"あんざんがん"},{"t":"の"},{"b":"集塊岩","f":"しゅうかいがん"},{"t":"、こっちは流紋凝灰岩です。"},{"b":"石灰","f":"せっかい"},{"t":"や"},{"b":"加里","f":"カリ"},{"t":"や"},{"b":"植物養料","f":"しょくぶつようりょう"},{"t":"がずうっと少いのです。ここにはとても杉なんか"},{"b":"育","f":"そだ"},{"t":"たないのです。〕うしろでふんふんうなずいているのは"},{"b":"藤原清作","f":"ふじわらせいさく"},{"t":"だ。あいつは"},{"b":"太田","f":"おおた"},{"t":"だからよくわかっているのだ。"}]},{"k":"p","r":[{"t":"〔"},{"b":"尤","f":"もっと"},{"t":"も向うの"},{"b":"杉","f":"すぎ"},{"t":"のついているところは"},{"b":"北側","f":"きたがわ"},{"t":"でこっちは南と東です。その"},{"b":"関係","f":"かんけい"},{"t":"もありますがそうでなくてもこっちは北側でも杉やひのきは"},{"b":"生","f":"は"},{"t":"えません。あすこの"},{"b":"崖","f":"がけ"},{"t":"で見てもわかります。この山と"},{"b":"地質","f":"ちしつ"},{"t":"は同じです。ただ北側なため"},{"b":"雑木","f":"ぞうき"},{"t":"が少しはよく"},{"b":"育","f":"そだ"},{"t":"ってます。〕いいや"},{"b":"駄目","f":"だめ"},{"t":"だ。おしまいのことを"},{"b":"云","f":"い"},{"t":"ったのは"},{"b":"結局","f":"けっきょく"},{"b":"混雑","f":"こんざつ"},{"t":"させただけだ。云わないでおけばよかった。それでもあの崖はほんとうの"},{"b":"嫩","f":"わか"},{"t":"い"},{"b":"緑","f":"みどり"},{"t":"や、"},{"b":"灰","f":"はい"},{"t":"いろの"},{"b":"芽","f":"め"},{"t":"や、"},{"b":"樺","f":"かば"},{"t":"の木の青やずいぶん"},{"b":"立派","f":"りっぱ"},{"t":"だ。"},{"b":"佐藤箴","f":"さとうかん"},{"t":"がとなりに"},{"b":"並","f":"なら"},{"t":"んで歩いてるな。"},{"b":"桜羽場","f":"さくらはば"},{"t":"がまた"},{"b":"凝灰岩","f":"ぎょうかいがん"},{"t":"を"},{"b":"拾","f":"ひろ"},{"t":"ったな。"},{"b":"頬","f":"ほお"},{"t":"がまっ"},{"b":"赤","f":"か"},{"t":"で"},{"b":"髪","f":"かみ"},{"t":"も"},{"b":"赭","f":"あか"},{"t":"いその小さな"},{"b":"子供","f":"こども"},{"t":"。"}]},{"k":"p","r":[{"t":"雲がきれて"},{"b":"陽","f":"ひ"},{"t":"が"},{"b":"照","f":"て"},{"t":"るしもう雨は"},{"b":"大丈夫","f":"だいじょうぶ"},{"t":"だ。さっきも"},{"b":"一遍","f":"いっぺん"},{"t":"云ったのだがもう"},{"b":"一度","f":"いちど"},{"t":"あの"},{"b":"禿","f":"はげ"},{"t":"の"},{"b":"所","f":"ところ"},{"t":"の"},{"b":"平","f":"ひら"},{"t":"べったい"},{"b":"松","f":"まつ"},{"t":"を"},{"b":"説明","f":"せつめい"},{"t":"しようかな。平ったくて黒い。"},{"b":"影","f":"かげ"},{"t":"も"},{"b":"落","f":"お"},{"t":"ちている。どこかであんなコロタイプを見た。"},{"b":"及川","f":"おいかわ"},{"t":"やなんか知ってるんだ。よすかな。いいや。やろう。"}]},{"k":"p","r":[{"t":"〔さあ、いいですか。あすこに大きな黄色の"},{"b":"禿","f":"は"},{"t":"げがあるでしょう。あすこの"},{"b":"割合","f":"わりあい"},{"t":"上のあたりに松が一本生えてましょう。平ったくてまるで"},{"b":"潰","f":"つぶ"},{"t":"れた"},{"b":"蕈","f":"きのこ"},{"t":"のようです。どうしてあんなになったんですか。"},{"b":"土壌","f":"どじょう"},{"t":"が"},{"b":"浅","f":"あさ"},{"t":"くて少し"},{"b":"根","f":"ね"},{"t":"をのばすとすぐ岩石でしょう。下へ"},{"b":"延","f":"の"},{"t":"びようとしても出来ないでしょう。"},{"b":"横","f":"よこ"},{"t":"に広がるだけでしょう。ところが根と"},{"b":"枝","f":"えだ"},{"t":"は"},{"b":"相関現象","f":"そうかんげんしょう"},{"t":"で"},{"b":"似","f":"に"},{"t":"たような形になるんです。枝も根のように横にひろがります。"},{"b":"桜","f":"さくら"},{"t":"の木なんか"},{"b":"植","f":"う"},{"t":"えるとき根を"},{"b":"束","f":"たば"},{"t":"ねるようにしてまっすぐに下げて植えると土から上の方も"},{"b":"箒","f":"ほうき"},{"t":"のように立ちましょう。広げれば広がります。〕"}]},{"k":"p","r":[{"t":"「そんだ。林学でおら"},{"b":"習","f":"なら"},{"t":"った。」何と"},{"b":"云","f":"い"},{"t":"ったかな。このせいの高い"},{"b":"眼","f":"め"},{"t":"の大きな"},{"b":"生徒","f":"せいと"},{"t":"。"}]},{"k":"p","r":[{"b":"坂","f":"さか"},{"t":"になったな。ごろごろ石が"},{"b":"落","f":"お"},{"t":"ちている。"}]},{"k":"p","r":[{"t":"「先生この石何て云うのす。」どうせきまってる。"}]},{"k":"p","r":[{"t":"〔凝灰岩。"},{"b":"流紋","f":"りゅうもん"},{"t":"凝灰岩だ。凝灰岩の"},{"b":"温泉","f":"おんせん"},{"t":"の"},{"b":"為","f":"ため"},{"t":"に"},{"b":"硅化","f":"けいか"},{"t":"を"},{"b":"受","f":"う"},{"t":"けたのだ。〕"}]},{"k":"p","r":[{"t":"光が"},{"b":"網","f":"あみ"},{"t":"になってゆらゆらする。みんなの"},{"b":"足並","f":"あしなみ"},{"t":"。小松の"},{"b":"密林","f":"みつりん"},{"t":"。"}]},{"k":"p","r":[{"t":"「"},{"b":"釜淵","f":"かまぶち"},{"t":"だら"},{"b":"俺","f":"おら"},{"t":"ぁ前になんぼがえりも見だ。それでも今日も来た。」"}]},{"k":"p","r":[{"t":"うしろで云っている。あの顔の赤い、そしていつでも少し眼が血走ってどうかすると"},{"b":"泣","f":"な"},{"t":"いているように見える、あの"},{"b":"生徒","f":"せいと"},{"t":"だ。"},{"b":"五内川","f":"ごないかわ"},{"t":"でもないし、何と云ったかな。"}]},{"k":"p","r":[{"t":"けれどもその"},{"b":"語","f":"ことば"},{"t":"はよく分っているぞ。よくわかっているとも。"}]},{"k":"p","r":[{"b":"巨礫","f":"きょれき"},{"t":"がごろごろしている。一つ"},{"b":"欠","f":"か"},{"t":"いて見せるかな。うまくいった。パチンといった。〔これは"},{"b":"安山岩","f":"あんざんがん"},{"t":"です。"},{"b":"上流","f":"かみ"},{"t":"の方から"},{"b":"流","f":"なが"},{"t":"れてきたのです。〕"}]},{"k":"p","r":[{"t":"すっと歩き出せ。"},{"b":"関","f":"せき"},{"t":"さんだ。「この石は安山岩であります。上流から流れてきたのです。」まねをしている。"},{"b":"堀田","f":"ほった"},{"t":"だな。堀田は赤い毛糸のジャケツを"},{"b":"着","f":"き"},{"t":"ているんだ。"},{"b":"物","f":"もの"},{"t":"を言う"},{"b":"口付","f":"くちつ"},{"t":"きが"},{"b":"覚束","f":"おぼつか"},{"t":"なくて"},{"b":"眼","f":"め"},{"t":"はどこを見ているかはっきりしないで黒くてうるんでいる。今はそれがうしろの"},{"b":"横","f":"よこ"},{"t":"でちらっと光る。"}]},{"k":"p","r":[{"t":"そこの"},{"b":"松林","f":"まつばやし"},{"t":"の中から黒い"},{"b":"畑","f":"はたけ"},{"t":"が一"},{"b":"枚","f":"まい"},{"t":"出てきます。"}]},{"k":"p","r":[{"t":"（ああ畑も入ります入ります。"},{"b":"遊園地","f":"ゆうえんち"},{"t":"には畑もちゃんと入ります）なんて"},{"b":"誰","f":"だれ"},{"t":"だったかな、"},{"b":"云","f":"い"},{"t":"っていた、あてにならない。こんな畑を云うんだろう。おれのはもっとずっと上流の"},{"b":"北上","f":"きたかみ"},{"t":"川から遠くの東の山地まで見はらせるようにあの"},{"b":"小桜","f":"こざくら"},{"t":"山の下の新らしく"},{"b":"墾","f":"ひら"},{"t":"いた広い畑を云ったんだ。"}]},{"k":"p","r":[{"t":"「"},{"b":"全体","f":"ぜんたい"},{"t":"どごさ行ぐのだべ。」"}]},{"k":"p","r":[{"t":"「なあに先生さ"},{"b":"従","f":"つ"},{"t":"いでさぃ行げばいいんだじゃ。」また堀田だな。前の通りだ。うしろで黄いろに光っている。みんな"},{"b":"躊躇","f":"ちゅうちょ"},{"t":"してみちをあけた。おれが一番さきになる。こっちもみちはよく知らないがなあにすぐそこなんだ。"},{"b":"路","f":"みち"},{"t":"から見えたら下りるだけだ。"},{"b":"防火線","f":"ぼうかせん"},{"t":"もずうっとうしろになった。"}]},{"k":"p","r":[{"t":"〔あれが小桜山だろう。〕けわしい二つの"},{"b":"稜","f":"りょう"},{"t":"を"},{"b":"持","f":"も"},{"t":"ち、"},{"b":"暗","f":"くら"},{"t":"くて雲かげにいる。少し名前に合わない。けれどもどこかしんとして春の"},{"b":"底","f":"そこ"},{"t":"の"},{"b":"樺","f":"かば"},{"t":"の木の気分はあるけれどもそれは"},{"b":"偶然性","f":"ぐうぜんせい"},{"t":"だ。よくわからない。みちが二つに"},{"b":"岐","f":"わか"},{"t":"れている。この下のみちがきっと"},{"b":"釜淵","f":"かまぶち"},{"t":"に行くんだ。もうきっと"},{"b":"間違","f":"まちが"},{"t":"いない。"}]},{"k":"p","r":[{"b":"小松","f":"こまつ"},{"t":"だ。"},{"b":"密","f":"みつ"},{"t":"だ。"},{"b":"混","f":"こ"},{"t":"んでいる。それから"},{"b":"巨礫","f":"きょれき"},{"t":"がごろごろしている。うすぐろくて安山岩だ。"},{"b":"地質調査","f":"ちしつちょうさ"},{"t":"をするときはこんなどこから来たかわからないあいまいな"},{"b":"岩石","f":"もの"},{"t":"に"},{"b":"鉄槌","f":"かなづち"},{"t":"を加えてはいけないと教えようかな。すぐ"},{"b":"眼","f":"め"},{"t":"の前を"},{"b":"及川","f":"おいかわ"},{"t":"が"},{"b":"手拭","f":"てぬぐい"},{"t":"を"},{"b":"首","f":"くび"},{"t":"に"},{"b":"巻","f":"ま"},{"t":"いて黄色の"},{"b":"服","f":"ふく"},{"t":"で"},{"b":"急","f":"いそ"},{"t":"いでいるし、"},{"b":"云","f":"い"},{"t":"おうかな。けれどもこれは"},{"b":"必要","f":"ひつよう"},{"t":"がない。"},{"b":"却","f":"かえ"},{"t":"って"},{"b":"混雑","f":"こんざつ"},{"t":"するだけだ。とにかくひどく"},{"b":"坂","f":"さか"},{"t":"になった。こんな"},{"b":"工合","f":"ぐあい"},{"t":"で"},{"b":"丁度","f":"ちょうど"},{"t":"よく"},{"b":"釜淵","f":"かまぶち"},{"t":"に下りるんだ。遠くで鳥も鳴いているし。下の方で"},{"b":"渓","f":"たに"},{"t":"がひどく鳴っている。ことによるとここらの下が釜淵だ。"},{"b":"一寸","f":"ちょっと"},{"t":"のぞいてみよう。"}]},{"k":"p","r":[{"t":"黒い"},{"b":"松","f":"まつ"},{"t":"の"},{"b":"幹","f":"みき"},{"t":"とかれくさ。みんなぞろぞろ"},{"b":"従","f":"つ"},{"t":"いてくる。渓が見える。水が見える。"},{"b":"波","f":"なみ"},{"t":"や白い"},{"b":"泡","f":"あわ"},{"t":"も見える。ああまだ下だ。ずうっと下だ。釜淵は。ふちの上の"},{"b":"滝","f":"たき"},{"t":"へ"},{"b":"平","f":"たい"},{"t":"らになって水がするする急いで行く。それさえずうっと下なのだ。"}]},{"k":"p","r":[{"t":"この"},{"b":"崖","f":"がけ"},{"t":"は急でとても下りられない。下に"},{"b":"降","f":"お"},{"t":"りよう。松林だ。みちらしく"},{"b":"踏","f":"ふ"},{"t":"まれたところもある。下りて行こう。"},{"b":"藪","f":"やぶ"},{"t":"だ。"},{"b":"日陰","f":"ひかげ"},{"t":"だ。"},{"b":"山吹","f":"やまぶき"},{"t":"の青いえだや何かもじゃもじゃしている。さきに行くのは"},{"b":"大内","f":"おおうち"},{"t":"だ。大内は夏服の上に黄色な"},{"b":"実習服","f":"じっしゅうふく"},{"t":"を"},{"b":"着","f":"き"},{"t":"て"},{"b":"結","f":"むす"},{"t":"びを"},{"b":"腰","f":"こし"},{"t":"にさげてずんずん藪をこいで行く。よくこいで行く。"}]},{"k":"p","r":[{"t":"急にけわしい"},{"b":"段","f":"だん"},{"t":"がある。木につかまれ木は光る。"},{"b":"雑木","f":"ぞうき"},{"t":"は二本雑木が光る。"}]},{"k":"p","r":[{"t":"「じゃ木さば"},{"b":"保","f":"た"},{"t":"ご"},{"b":"附","f":"つ"},{"t":"くこなしだじゃぃ。」"},{"b":"誰","f":"だれ"},{"t":"かがうしろで"},{"b":"叫","f":"さけ"},{"t":"んでいる。どういう"},{"b":"意味","f":"いみ"},{"t":"かな。木にとりつくと"},{"b":"弾","f":"は"},{"t":"ね"},{"b":"返","f":"かえ"},{"t":"ってうしろのものを"},{"b":"叩","f":"たた"},{"t":"くというのだろうか。"}]},{"k":"p","r":[{"t":"光って木がはねかえる。おれはそんなことをしたかな。いやそれはもうよく気をつけたんだ。藪だ。もじゃもじゃしている。大内はよくあるく。"}]},{"k":"p","r":[{"b":"崖","f":"がけ"},{"t":"だ。"},{"b":"滝","f":"たき"},{"t":"はすぐそこだし、ここを下りるより"},{"b":"仕方","f":"しかた"},{"t":"ない。さあ降りよう。大内はよく降りて行く。急だぞ。この木は少し太すぎる。"},{"b":"灰","f":"はい"},{"t":"いろだ。急だぞ、草、この木は細いぞ、青いぞあぶないぞ。なかなか急だ。"},{"b":"大丈夫","f":"だいじょうぶ"},{"t":"だ。この木は切ってあるぞ。〔ほう、〕そこはあんまり急だ。"}]},{"k":"p","r":[{"t":"おりるのか。仕方ない。木がめまぐるしいぞ。「一人"},{"b":"落","f":"お"},{"t":"ぢればみんな落ぢるぞ。」誰かうしろで叫んでいる。落ちてきたら"},{"b":"全","f":"まった"},{"t":"くみんな落ちる。大内がずうっと落ちた。"}]},{"k":"p","r":[{"b":"河原","f":"かわら"},{"t":"まで行ってやっととまった。"}]},{"k":"p","r":[{"t":"おれはとにかく"},{"b":"首尾","f":"しゅび"},{"t":"よく"},{"b":"降","f":"お"},{"t":"りた。"}]},{"k":"blank"},{"k":"p","r":[{"t":"少し下へさがり"},{"b":"過","f":"す"},{"t":"ぎた。"},{"b":"瀑","f":"たき"},{"t":"まで行くみちはない。"}]},{"k":"p","r":[{"b":"凝灰岩","f":"ぎょうかいがん"},{"t":"が青じろく崖と"},{"b":"波","f":"なみ"},{"t":"との間に四、五"},{"b":"寸","f":"すん"},{"b":"続","f":"つづ"},{"t":"いてはいるけれどもとてもあすこは"},{"b":"伝","f":"つた"},{"t":"って行けない。それよりはやっぱり水を"},{"b":"渉","f":"わた"},{"t":"って"},{"b":"向","f":"むこ"},{"t":"うへ行くんだ。向うの河原は"},{"b":"可成","f":"かなり"},{"t":"広いし"},{"b":"滝","f":"たき"},{"t":"までずうっと続いている。"}]},{"k":"p","r":[{"t":"けれども"},{"b":"脚","f":"あし"},{"t":"はやっぱりぬれる。"},{"b":"折角","f":"せっかく"},{"t":"ぬらさないためにまわり道して上から来たのだ、"},{"b":"飛石","f":"とびいし"},{"t":"を一つこさえてやるかな。二つはそのまま"},{"b":"使","f":"つか"},{"t":"えるしもう四つだけころがせばいい、まずおれは"},{"b":"靴","f":"くつ"},{"t":"をぬごう。ゴム靴によごれた青の靴下か。〔"},{"b":"一寸","f":"ちょっと"},{"b":"待","f":"ま"},{"t":"って、今"},{"b":"渡","f":"わた"},{"t":"るようにしますから。〕"}]},{"k":"p","r":[{"t":"この石は"},{"b":"動","f":"うご"},{"t":"かせるかな。"},{"b":"流紋岩","f":"りゅうもんがん"},{"t":"だかなりの"},{"b":"比重","f":"ひじゅう"},{"t":"だ。動くだろう。水の中だし、アルキメデス、水の中だし、動く動く。うまくいった。"},{"b":"波","f":"なみ"},{"t":"、これも"},{"b":"大丈夫","f":"だいじょうぶ"},{"t":"だ。大丈夫。"},{"b":"引率","f":"いんそつ"},{"t":"の教師が飛石をつくるのもおかしいがまたえらい。やっぱりおかしい。ありがたい。うまくいった。"}]},{"k":"p","r":[{"t":"ひとりが渡る。ぐらぐらする。あぶなく渡る、二人がわたる。"}]},{"k":"p","r":[{"t":"もう一つはどれにするかな　もう四人だけ渡っている。飛石の上に"},{"b":"両","f":"りょう"},{"t":"あしを"},{"b":"揃","f":"そろ"},{"t":"えてきちんと立って四人つづいて"},{"b":"待","f":"ま"},{"t":"っているのは"},{"b":"面白","f":"おもしろ"},{"t":"い。向うの河原のを動かそう。"},{"b":"影","f":"かげ"},{"t":"のある石だ。"}]},{"k":"p","r":[{"b":"持","f":"も"},{"t":"てるかな。持てる。けれども"},{"b":"一番","f":"いちばん"},{"t":"波の強いところだ。"},{"b":"恐","f":"おそ"},{"t":"らく少し小さいぞ。小さい。波が"},{"b":"昆布","f":"こんぶ"},{"t":"だ、"},{"b":"越","f":"こ"},{"t":"して行く。もう一つ持って来よう。こいつは"},{"b":"苔","f":"こけ"},{"t":"でぬるぬるしている。これで二つだ。まだぐらぐらだ。も一つ"},{"b":"要","f":"い"},{"t":"る。小さいけれども台にはなる。大丈夫だ。おれははだしで行こうかな。いいややっぱり靴ははこう。"},{"b":"面倒","f":"めんどう"},{"t":"くさい靴下はポケットへ"},{"b":"押","f":"お"},{"t":"し"},{"b":"込","f":"こ"},{"t":"め、ポケットがふくれて"},{"b":"気持","f":"きも"},{"t":"ちがいいぞ。"}]},{"k":"p","r":[{"b":"素","f":"す"},{"t":"あしにゴム"},{"b":"靴","f":"ぐつ"},{"t":"でぴちゃぴちゃ水をわたる。これはよっぽどいいことになっている。前にも一ぺんどこかでこんなことがあった。"},{"b":"去年","f":"きょねん"},{"t":"の秋だ。"},{"b":"腐植質","f":"フィウマス"},{"t":"の野原のたまり水だったかもしれない。"},{"b":"向","f":"むこ"},{"t":"うに黒いみちがある。"},{"b":"崖","f":"がけ"},{"t":"の"},{"b":"茂","f":"しげ"},{"t":"みにはいって行く。これが"},{"b":"羽山","f":"はやま"},{"t":"を"},{"b":"越","f":"こ"},{"t":"えて台に"},{"b":"出","f":"で"},{"t":"るのかもわからない。帰りに"},{"b":"登","f":"のぼ"},{"t":"るとしようかな。いいや。だめだ。"},{"b":"曖昧","f":"あいまい"},{"t":"だしそれにみんなも越えれまい。"}]},{"k":"p","r":[{"t":"「先生、この石何す。」一かけひろって"},{"b":"持","f":"も"},{"t":"っている。〔ふん。何だと思います。〕「何だべな。」〔"},{"b":"凝灰岩","f":"ぎょうかいがん"},{"t":"です。ここらはみんなそうですよ。"},{"b":"浮岩質","f":"ふがんしつ"},{"t":"の凝灰岩。〕"}]},{"k":"p","r":[{"t":"みんなさっきはあしをぬらすまいとしたんだが日が"},{"b":"照","f":"て"},{"t":"るし水はきれいだし自分でも気がつかず川にはいったんだ。"}]},{"k":"p","r":[{"t":"もうずんずん"},{"b":"瀑","f":"たき"},{"t":"をのぼって行く。cascade だ。こんな広い"},{"b":"平","f":"たい"},{"t":"らな明るい瀑はありがたい。上へ行ったらもっと平らで明るいだろう。けれども"},{"b":"壺穴","f":"つぼあな"},{"t":"の"},{"b":"標本","f":"ひょうほん"},{"t":"を見せるつもりだったが思ったくらいはっきりはしていないな。多少"},{"b":"失望","f":"しつぼう"},{"t":"だ。岩は何という円くなめらかに"},{"b":"削","f":"けず"},{"t":"られたもんだろう。"},{"b":"水苔","f":"みずごけ"},{"t":"も"},{"b":"生","f":"は"},{"t":"えている。"},{"b":"滑","f":"すべ"},{"t":"るだろうか。滑らない。ゴム靴の"},{"b":"底","f":"そこ"},{"t":"のざりざりの"},{"b":"摩擦","f":"まさつ"},{"t":"がはっきり知れる。滑らない。"},{"b":"大丈夫","f":"だいじょうぶ"},{"t":"だ。さらさら水が"},{"b":"落","f":"お"},{"t":"ちている。靴はビチャビチャ"},{"b":"云","f":"い"},{"t":"っている。みんないい。それにみんなは後からついて来る。"}]},{"k":"p","r":[{"t":"苔がきれいにはえている。"},{"b":"実","f":"じつ"},{"t":"に円く"},{"b":"柔","f":"やわ"},{"t":"らかに水がこの瀑のところを"},{"b":"削","f":"けず"},{"t":"ったもんだ。この"},{"b":"浸蝕","f":"しんしょく"},{"t":"の柔らかさ。"}]},{"k":"blank"},{"k":"p","r":[{"t":"もう平らだ。そうだ。いつかもここを"},{"b":"溯","f":"のぼ"},{"t":"って行った。いいや、"},{"b":"此処","f":"ここ"},{"t":"じゃない。けれどもずいぶんよく"},{"b":"似","f":"に"},{"t":"ているぞ。川の広さも"},{"b":"両岸","f":"りょうがん"},{"t":"の崖、ところどころの"},{"b":"洲","f":"す"},{"t":"の青草。もう平らだ。みんな大分溯ったな。"}]},{"k":"p","r":[{"t":"〔ここをごらんなさい。岩石の"},{"b":"裂","f":"さ"},{"t":"け目に"},{"b":"沿","f":"そ"},{"t":"って赤く色が"},{"b":"変","f":"かわ"},{"t":"っているでしょう。裂け目のないところにも赤い"},{"b":"条","f":"すじ"},{"t":"の通っているところがあるでしょう。この裂け目を"},{"b":"温泉","f":"おんせん"},{"t":"が通ったのです。温泉の作用で岩が赤くなったのです。ここがずうっとつちの"},{"b":"底","f":"そこ"},{"t":"だったときですよ。わかりますか。〕"}]},{"k":"p","r":[{"t":"だまっている。"},{"b":"波","f":"なみ"},{"t":"がうごき波が足をたたく。日光が"},{"b":"降","f":"ふ"},{"t":"る。この水を"},{"b":"渉","f":"わた"},{"t":"ることの"},{"b":"快","f":"こころよ"},{"t":"さ。"},{"b":"菅木","f":"すがき"},{"t":"がいるな。いつものようにじっとひとの目を見つめている。"}]},{"k":"p","r":[{"t":"〔ここをごらんなさい。岩に"},{"b":"裂","f":"さ"},{"t":"け目があるでしょう。ここを"},{"b":"温泉","f":"おんせん"},{"t":"が通って岩を"},{"b":"変質","f":"へんしつ"},{"t":"させたのです。"},{"b":"風化","f":"ふうか"},{"t":"のためにもこう"},{"b":"云","f":"い"},{"t":"う赤い"},{"b":"縞","f":"しま"},{"t":"はできます。けれどもここではほかのことから温泉の作用ということがわかるのです。〕"}]},{"k":"p","r":[{"t":"ずいぶん"},{"b":"上流","f":"じょうりゅう"},{"t":"まで行った。"},{"b":"実際","f":"じっさい"},{"t":"こんなに"},{"b":"川床","f":"かわどこ"},{"t":"が"},{"b":"平","f":"たい"},{"t":"らで水もきれいだし山の中の"},{"b":"第一流","f":"だいいちりゅう"},{"t":"の"},{"b":"道路","f":"どうろ"},{"t":"だ。どこまでものぼりたいのはあたりまえだ。"}]},{"k":"p","r":[{"b":"向","f":"むこ"},{"t":"うの"},{"b":"岸","f":"きし"},{"t":"の方にうつろう。"}]},{"k":"p","r":[{"t":"「先生この岩何す。」"},{"b":"千葉","f":"ちば"},{"t":"だな。お父さんによく"},{"b":"似","f":"に"},{"t":"ている。〔何に似てます。何でできてますか。〕だまっている。〔わかりませんか。"},{"b":"礫岩","f":"れきがん"},{"t":"です。礫岩です。"},{"b":"凝灰質礫岩","f":"ぎょうかいしつれきがん"},{"t":"。〕"},{"b":"及川","f":"おいかわ"},{"t":"だな。〔いいですか。これは"},{"b":"温泉","f":"おんせん"},{"t":"の作用ですよ。この裂け目を通った温泉のために凝灰岩が"},{"b":"変質","f":"へんしつ"},{"t":"を"},{"b":"受","f":"う"},{"t":"けたんです。〕"}]},{"k":"p","r":[{"t":"みんなわかるんだな。これは。向うにも一つ"},{"b":"滝","f":"たき"},{"t":"があるらしい。うすぐろい岩の。みんなそこまで行こうと云うのか。草原があって春木も"},{"b":"積","f":"つ"},{"t":"んである。ずいぶん"},{"b":"溯","f":"のぼ"},{"t":"ったぞ。ここは小さな"},{"b":"段","f":"だん"},{"t":"だ。"}]},{"k":"p","r":[{"t":"「ああ云う岩のすき間のごと何て云うのだたべな。"},{"b":"習","f":"なら"},{"t":"ったたんとも。」"}]},{"k":"p","r":[{"t":"〔やっぱり裂け目です。裂け目でいいんです。〕習ったというのは"},{"b":"節理","f":"せつり"},{"t":"だな。節理なら"},{"b":"多面","f":"ためん"},{"t":"節理、これを節理と云うわけにはいかない。"},{"b":"裂罅","f":"れっか"},{"t":"だ。やっぱり裂け目でいいんだ。"},{"b":"壺穴","f":"つぼあな"},{"t":"のいいのがなくて"},{"b":"困","f":"こま"},{"t":"るな。少し細長いけれどもこれで"},{"b":"説明","f":"せつめい"},{"t":"しようか。elongatedpot-hole〔ここがどうしてこう"},{"b":"掘","f":"ほ"},{"t":"れるかわかりますか。石ころ、礫がこれを掘るのです。そら水のために礫がごろごろするでしょう。だんだん岩を掘るでしょう。"},{"b":"深","f":"ふか"},{"t":"いところが"},{"b":"一層","f":"いっそう"},{"t":"深くなるはずです。もっと大きなのもあります。〕"}]},{"k":"p","r":[{"t":"日光の波、日光の波、光の"},{"b":"網","f":"あみ"},{"t":"と、水の網。"}]},{"k":"p","r":[{"t":"「ほこの"},{"b":"穴","f":"あな"},{"t":"こまん円けじゃ。先生。」"}]},{"k":"p","r":[{"t":"ああいい、これはいい"},{"b":"標本","f":"ひょうほん"},{"t":"だ。こいつなら"},{"b":"持","f":"も"},{"t":"ってこいだ。"}]},{"k":"p","r":[{"t":"〔さあ、見て下さい。これはいい標本です。そら。この中に石ころが入ってましょう。みんな円くなってるでしょう。水ががりがり"},{"b":"擦","f":"こす"},{"t":"ったんです。そら。〕"}]},{"k":"p","r":[{"b":"実","f":"じつ"},{"t":"にいい"},{"b":"礫","f":"れき"},{"t":"だ。まっ白だ。まん円だ水でぬれている。"},{"b":"取","f":"と"},{"t":"ってしまった。"},{"b":"誰","f":"だれ"},{"t":"かがまた"},{"b":"掻","f":"か"},{"t":"き"},{"b":"廻","f":"まわ"},{"t":"す。もうない。あとは茶色だし少し角もある。ああいいな。こんなありがたい。あんまり"},{"b":"溯","f":"のぼ"},{"t":"る。もう帰ろう。校長もあの"},{"b":"路","f":"みち"},{"t":"の"},{"b":"岐","f":"わか"},{"t":"れ目で"},{"b":"待","f":"ま"},{"t":"っている。"}]},{"k":"p","r":[{"t":"〔ほう。"},{"b":"戻","f":"もど"},{"t":"れ。ほう。〕"},{"b":"向","f":"むこ"},{"t":"うの"},{"b":"崖","f":"がけ"},{"t":"は明るいし声はよく出ない。聞えないようだ。"},{"b":"市野川","f":"いちのかわ"},{"t":"やぐんぐんのぼって行く。〔ほう、〕「戻れど。お。」「戻れ。」"}]},{"k":"p","r":[{"t":"向いた向いた。一人向けばもういい。川を戻るよりはここからさっきの道へのぼったほうがいい、"},{"b":"傾斜","f":"けいしゃ"},{"t":"もゆるく"},{"b":"丁度","f":"ちょうど"},{"t":"のぼれそうだ。〔みんなそこからあの道へ出ろ。〕"}]},{"k":"p","r":[{"t":"手を"},{"b":"振","f":"ふ"},{"t":"ったほうがわかるな。わかったわかったわかったようだ。市野川が崖の上のみちを見ている。"}]},{"k":"p","r":[{"t":"うしろの"},{"b":"滝","f":"たき"},{"t":"の上で"},{"b":"誰","f":"だれ"},{"t":"か"},{"b":"叫","f":"さけ"},{"t":"んでいる。"},{"b":"大竹","f":"おおたけ"},{"t":"だ。「おら"},{"b":"荷物","f":"にもつ"},{"b":"置","f":"お"},{"t":"いてきたがらこっちがら行ぐ。」よかろう。〔よおし。〕もう大竹が滝をおりて行く。すばやいやつだ。二、三人またついて行く。それからも一人おくれてひどく"},{"b":"心配","f":"しんぱい"},{"t":"そうに"},{"b":"背中","f":"せなか"},{"t":"をかがめて下りていく。"},{"b":"斉藤貞一","f":"さいとうていいち"},{"t":"かな。"},{"b":"一寸","f":"ちょっと"},{"t":"こっちを見たところには"},{"b":"栗鼠","f":"りす"},{"t":"の"},{"b":"軽","f":"かる"},{"t":"さもある。ほんとうに心配なんだ。かあいそう。"}]},{"k":"p","r":[{"t":"市野川やみんながぞろぞろ崖をみちの方へ上って行くらしい。"}]},{"k":"p","r":[{"t":"そうすればおれはやっぱり川を下ったほうがいいんだ。もしも誰か"},{"b":"途中","f":"とちゅう"},{"t":"で止っていてはわるい。"},{"b":"尤","f":"もっと"},{"t":"も"},{"b":"靴下","f":"くつした"},{"t":"もポケットに入っているし"},{"b":"必","f":"かなら"},{"t":"ず下らなければならないということはない、けれどもやっぱりこっちを行こう。ああいい"},{"b":"気持","f":"きもち"},{"t":"だ。"},{"b":"鉄槌","f":"かなづち"},{"t":"をこんなに大きく振って川をあるくことはもう何年ぶりだろう。"},{"b":"波","f":"なみ"},{"t":"が足をあらい水はつめたく"},{"b":"陽","f":"ひ"},{"t":"は"},{"b":"射","f":"さ"},{"t":"している。"}]},{"k":"p","r":[{"t":"「先生ぁ、ずいぶん足ぁ早ぃな。」"},{"b":"富手","f":"とみて"},{"t":"かな、"},{"b":"菅木","f":"すがき"},{"t":"かな、あんなことを"},{"b":"云","f":"い"},{"t":"っている。足が早いというのは道をあるくときの話だ。ここも"},{"b":"平","f":"たい"},{"t":"らで"},{"b":"上等","f":"じょうとう"},{"t":"の歩道なのだ。ただ水があるばかり。"}]},{"k":"p","r":[{"t":"「先生、あの"},{"b":"崖","f":"がけ"},{"t":"のどご色"},{"b":"変","f":"かわ"},{"t":"ってるのぁ何してす。」"},{"b":"簡","f":"かん"},{"t":"だ。崖の色か。"}]},{"k":"p","r":[{"t":"〔あれは"},{"b":"向","f":"むこ"},{"t":"うだけは土が"},{"b":"落","f":"お"},{"t":"ちたんです。"},{"b":"滑","f":"すべ"},{"t":"って。〕"}]},{"k":"p","r":[{"t":"うん。あるある。これが"},{"b":"裂罅","f":"れっか"},{"t":"を"},{"b":"温泉","f":"おんせん"},{"t":"の通った"},{"b":"証拠","f":"しょうこ"},{"t":"だ。"},{"b":"玻璃蛋白石","f":"はりたんぱくせき"},{"t":"の"},{"b":"脈","f":"みゃく"},{"t":"だ。"}]},{"k":"p","r":[{"t":"〔ここをごらんなさい。岩のさけ目に白いものがつまっているでしょう。これは温泉から"},{"b":"沈澱","f":"ちんでん"},{"t":"したのです。"},{"b":"石英","f":"せきえい"},{"t":"です。岩のさけ目を白いものが"},{"b":"埋","f":"う"},{"t":"めているでしょう。いい"},{"b":"標本","f":"ひょうほん"},{"t":"です。〕みんなが"},{"b":"囲","f":"かこ"},{"t":"む。水の中だ。"}]},{"k":"p","r":[{"t":"「"},{"b":"取","f":"と"},{"t":"らえなぃがべが。」「いいや、"},{"b":"此処","f":"ここ"},{"t":"このまんまの標本だ。」"}]},{"k":"p","r":[{"t":"「それでも取らえなぃがべが。」〔取ってみますか。取れます。〕"}]},{"k":"p","r":[{"t":"中々"},{"b":"面倒","f":"めんどう"},{"t":"だ。"}]},{"k":"p","r":[{"t":"「先生こっちにもっと大きなのあるんす。」あるある。これならネストと"},{"b":"云","f":"い"},{"t":"ってもいい。これなら取れる。ハムマアの"},{"b":"尖","f":"とが"},{"t":"った方ではだめだ。"},{"b":"平","f":"ひら"},{"t":"たい方は……。"}]},{"k":"p","r":[{"t":"水がぴちゃぴちゃはねる。そっちの方のものが"},{"b":"逃","f":"に"},{"t":"げる、ふん。"}]},{"k":"p","r":[{"t":"〔水がはねますか。やっぱりこっちでやるかな。〕"}]},{"k":"p","r":[{"t":"白く岩に"},{"b":"傷","f":"きず"},{"t":"がついた。"},{"b":"二所","f":"ふたところ"},{"t":"ついた。"}]},{"k":"p","r":[{"t":"とれる。とれた。うまい。"},{"b":"新鮮","f":"しんせん"},{"t":"だ。青白い。"}]},{"k":"p","r":[{"b":"緑簾石","f":"りょくれんせき"},{"t":"もついている。そうじゃないこれは"},{"b":"苔","f":"こけ"},{"t":"だ。〔いいですか。これは玻璃蛋白石です。温泉から沈澱したのです。"},{"b":"晶洞","f":"しょうどう"},{"t":"もあります。小さな石英の"},{"b":"結晶","f":"けっしょう"},{"t":"です。"},{"b":"持","f":"も"},{"t":"っておいでなさい。〕"}]},{"k":"p","r":[{"b":"誰","f":"だれ"},{"t":"だ"},{"b":"崖","f":"がけ"},{"t":"の上で"},{"b":"叫","f":"さけ"},{"t":"んでいるのは。"}]},{"k":"p","r":[{"t":"「先生。おら"},{"b":"河童捕","f":"かっぱど"},{"t":"りしたもや。河童捕り。」"},{"b":"藤原健太郎","f":"ふじわらけんたろう"},{"t":"だ。黒の"},{"b":"制服","f":"せいふく"},{"t":"を"},{"b":"着","f":"き"},{"t":"て"},{"b":"雑嚢","f":"ざつのう"},{"t":"をさげ、ひどくはしゃいで"},{"b":"笑","f":"わら"},{"t":"っている。どうしていまごろあんな崖の上などに顔を出したのだ。"}]},{"k":"p","r":[{"t":"「先生。下りで行ぐべがな。先生。よし、下りで行ぐぞ。」"}]},{"k":"p","r":[{"t":"〔うん。"},{"b":"大丈夫","f":"だいじょうぶ"},{"t":"。大丈夫だ。〕おりるおりる。がりがりやって来るんだな。ただそのおしまいの一足だけがあぶないぞ。"},{"b":"裸","f":"はだか"},{"t":"の青い岩だし"},{"b":"急","f":"きゅう"},{"t":"だ。"}]},{"k":"p","r":[{"t":"〔おおい。もう少し"},{"b":"斜","f":"ななめ"},{"t":"におりろ。〕おりるおりる。どんどん下りる。もう水へ入った。〔どうしたのです。〕「先生。河童捕りあ"},{"g":"〓","d":"小書き平仮名ん、135-11"},{"t":"すた。ガバンも何も、すっかりぬらすたも。」〔どこで。……〕"}]},{"k":"p","r":[{"t":"もう下ろう。"},{"b":"滝","f":"たき"},{"t":"に来た。下りているものもある。水の"},{"b":"流","f":"なが"},{"t":"れる"},{"b":"所","f":"ところ"},{"t":"は"},{"b":"苔","f":"こけ"},{"t":"は青く流れない所は"},{"b":"褐色","f":"かっしょく"},{"t":"だ。みんなこわごわ下りて来る。水の流れる所は大丈夫"},{"b":"滑","f":"すべ"},{"t":"らないんだ。〔水の流れるところをあるきなさい。水の流れるところがいいんです。〕"}]},{"k":"p","r":[{"t":"あれは"},{"b":"葛丸","f":"くずまる"},{"t":"川だ。足をさらわれて"},{"b":"淵","f":"ふち"},{"t":"に入ったのは。いいや葛丸川じゃない。"},{"b":"空想","f":"くうそう"},{"t":"のときの"},{"b":"暗","f":"くら"},{"t":"い谷だ。どっちでもいい。水がさあさあ"},{"b":"云","f":"い"},{"t":"っている。「いいな。あそごの水の"},{"b":"跳","f":"は"},{"t":"ね"},{"b":"返","f":"かえ"},{"t":"る"},{"b":"処","f":"ところ"},{"t":"よ。」"}]},{"k":"p","r":[{"t":"うん、いい"},{"b":"早池峯山","f":"はやちねさん"},{"t":"の"},{"b":"七折","f":"ななおり"},{"t":"の"},{"b":"滝","f":"たき"},{"t":"だってこんなのの大きなだけだろう。"}]},{"k":"p","r":[{"t":"もうみんなおりる。おれもおりる。たった一人あとからやって来る人がある。こわそうだ。"}]},{"k":"p","r":[{"t":"〔水の流れるところをあるくんです。水の流れる所を歩くんですよ。〕"}]},{"k":"p","r":[{"t":"そうだ。そうだ。いい"},{"b":"気持","f":"きも"},{"t":"ちだ。"}]}]}