{"id":"050983","title":"不死の薬","author":"小川未明","authorId":"001475","blocks":[{"k":"h","level":2,"r":[{"t":"一"}]},{"k":"blank"},{"k":"p","r":[{"t":"　ある"},{"b":"夏","f":"なつ"},{"t":"の"},{"b":"夜","f":"よる"},{"t":"でありました。三"},{"b":"人","f":"にん"},{"t":"の"},{"b":"子供","f":"こども"},{"t":"らが"},{"b":"村","f":"むら"},{"t":"の"},{"b":"中","f":"うち"},{"t":"にあった"},{"b":"大","f":"おお"},{"t":"きなかしの"},{"b":"木","f":"き"},{"t":"の"},{"b":"下","f":"した"},{"t":"に"},{"b":"集","f":"あつ"},{"t":"まって"},{"b":"話","f":"はなし"},{"t":"をしました。"},{"b":"昼間","f":"ひるま"},{"t":"の"},{"b":"暑","f":"あつ"},{"t":"さにひきかえて、"},{"b":"夜","f":"よる"},{"t":"は"},{"b":"涼","f":"すず"},{"t":"しくありました。ことにこの"},{"b":"木","f":"き"},{"t":"の"},{"b":"下","f":"した"},{"t":"は"},{"b":"風","f":"かぜ"},{"t":"があって"},{"b":"涼","f":"すず"},{"t":"しゅうございました。"}]},{"k":"p","r":[{"t":"　"},{"b":"赤","f":"あか"},{"t":"く"},{"b":"西","f":"にし"},{"t":"の"},{"b":"山","f":"やま"},{"t":"に"},{"b":"日","f":"ひ"},{"t":"が"},{"b":"沈","f":"しず"},{"t":"んでしまって、ほんのりと"},{"b":"紅","f":"あか"},{"t":"い"},{"b":"雲","f":"くも"},{"t":"がいつまでも"},{"b":"消","f":"き"},{"t":"えずに、"},{"b":"林","f":"はやし"},{"t":"の"},{"b":"間","f":"あいだ"},{"t":"に"},{"b":"残","f":"のこ"},{"t":"っていましたが、それすらまったく"},{"b":"消","f":"き"},{"t":"えてしまいました。"},{"b":"夜","f":"よる"},{"t":"の"},{"b":"空","f":"そら"},{"t":"は"},{"b":"深","f":"ふか"},{"t":"い"},{"b":"沼","f":"ぬま"},{"t":"の"},{"b":"中","f":"なか"},{"t":"をのぞくように"},{"b":"青黒","f":"あおぐろ"},{"t":"く"},{"b":"見","f":"み"},{"t":"えました。そのうちに、だんだん"},{"b":"星","f":"ほし"},{"t":"の"},{"b":"光","f":"ひかり"},{"t":"がたくさんになって"},{"b":"見","f":"み"},{"t":"えてきました。"}]},{"k":"p","r":[{"t":"「さあ、またなにかおとぎ"},{"b":"噺","f":"ばなし"},{"t":"をしようよ。」"}]},{"k":"p","r":[{"t":"と"},{"b":"乙","f":"おつ"},{"t":"がいいました。"}]},{"k":"p","r":[{"t":"「"},{"b":"今日","f":"きょう"},{"t":"は"},{"b":"丙","f":"へい"},{"t":"の"},{"b":"番","f":"ばん"},{"t":"だよ。」"}]},{"k":"p","r":[{"t":"と"},{"b":"甲","f":"こう"},{"t":"がいいました。"}]},{"k":"p","r":[{"t":"　この三"},{"b":"人","f":"にん"},{"t":"は"},{"b":"同","f":"おな"},{"t":"じ"},{"b":"村","f":"むら"},{"t":"の"},{"b":"小学校","f":"しょうがっこう"},{"t":"へいっている、"},{"b":"同","f":"おな"},{"t":"じ"},{"b":"年","f":"とし"},{"t":"ごろの"},{"b":"少年","f":"しょうねん"},{"t":"で、いたって"},{"b":"仲","f":"なか"},{"t":"がよく、いろいろの"},{"b":"遊","f":"あそ"},{"t":"びをしましたが、この"},{"b":"夏","f":"なつ"},{"t":"の"},{"b":"晩","f":"ばん"},{"t":"には、このかしの"},{"b":"木","f":"き"},{"t":"の"},{"b":"下","f":"した"},{"t":"にきて、"},{"b":"自分","f":"じぶん"},{"t":"らが"},{"b":"聞","f":"き"},{"t":"いたり、"},{"b":"覚","f":"おぼ"},{"t":"えていたりしているいろいろのおとぎ"},{"b":"噺","f":"ばなし"},{"t":"をしあって"},{"b":"遊","f":"あそ"},{"t":"びました。"}]},{"k":"p","r":[{"t":"　このとき、かしの"},{"b":"木","f":"き"},{"t":"の"},{"b":"葉","f":"は"},{"t":"が、さらさらといって、"},{"b":"青黒","f":"あおぐろ"},{"t":"いガラスのような"},{"b":"空","f":"そら"},{"t":"で"},{"b":"鳴","f":"な"},{"t":"りました。三"},{"b":"人","f":"にん"},{"t":"はしばらく"},{"b":"黙","f":"だま"},{"t":"っていましたが、"},{"b":"乙","f":"おつ"},{"t":"が"},{"b":"丙","f":"へい"},{"t":"に"},{"b":"向","f":"む"},{"t":"かって、"}]},{"k":"p","r":[{"t":"「さあ"},{"b":"君","f":"きみ"},{"t":"、なにか"},{"b":"話","f":"はな"},{"t":"してくれたまえ。」"}]},{"k":"p","r":[{"t":"といいました。"}]},{"k":"p","r":[{"t":"　三"},{"b":"人","f":"にん"},{"t":"の"},{"b":"中","f":"うち"},{"t":"のもっとも"},{"b":"年下","f":"としした"},{"t":"の"},{"b":"丙","f":"へい"},{"t":"は、"},{"b":"空","f":"そら"},{"t":"を"},{"b":"見","f":"み"},{"t":"て"},{"b":"考","f":"かんが"},{"t":"えていました。このとき、"},{"b":"遠","f":"とお"},{"t":"く"},{"b":"北","f":"きた"},{"t":"の"},{"b":"方","f":"ほう"},{"t":"の"},{"b":"海","f":"うみ"},{"t":"で"},{"b":"汽笛","f":"きてき"},{"t":"の"},{"b":"音","f":"おと"},{"t":"がかすかに"},{"b":"聞","f":"き"},{"t":"こえたのでありました。三"},{"b":"人","f":"にん"},{"t":"はまたその"},{"b":"音","f":"おと"},{"t":"を"},{"b":"聞","f":"き"},{"t":"いて"},{"b":"心","f":"こころ"},{"t":"の"},{"b":"中","f":"うち"},{"t":"でいろいろの"},{"b":"空想","f":"くうそう"},{"t":"にふけりました。"}]},{"k":"p","r":[{"t":"「さあ"},{"b":"話","f":"はな"},{"t":"すよ。」"}]},{"k":"p","r":[{"t":"と"},{"b":"丙","f":"へい"},{"t":"はいった。そのりこうそうな"},{"b":"黒","f":"くろ"},{"t":"いかわいらしい"},{"b":"目","f":"め"},{"t":"に"},{"b":"星","f":"ほし"},{"t":"の"},{"b":"光","f":"ひかり"},{"t":"がさしてひらめきました。"}]},{"k":"p","r":[{"t":"「ああ、"},{"b":"聞","f":"き"},{"t":"くよ、"},{"b":"早","f":"はや"},{"t":"く"},{"b":"話","f":"はな"},{"t":"したまえ。」"}]},{"k":"p","r":[{"t":"と"},{"b":"甲","f":"こう"},{"t":"も"},{"b":"乙","f":"おつ"},{"t":"もいいました。"}]},{"k":"p","r":[{"t":"　"},{"b":"丙","f":"へい"},{"t":"は、つぎのような"},{"b":"話","f":"はなし"},{"t":"をしました。……"}]},{"k":"p","r":[{"t":"　"},{"b":"昔","f":"むかし"},{"t":"、"},{"b":"支那","f":"しな"},{"t":"に、ある"},{"b":"天子","f":"てんし"},{"t":"さまがあって、すべての"},{"b":"国","f":"くに"},{"t":"をたいらげられて、りっぱな"},{"b":"御殿","f":"ごてん"},{"t":"を"},{"b":"建","f":"た"},{"t":"てて、"},{"b":"栄誉","f":"えいよ"},{"t":"・"},{"b":"栄華","f":"えいが"},{"t":"な"},{"b":"日","f":"ひ"},{"t":"を"},{"b":"送","f":"おく"},{"t":"られました。"},{"b":"天子","f":"てんし"},{"t":"さまはなにひとつ"},{"b":"自分","f":"じぶん"},{"t":"の"},{"b":"思","f":"おも"},{"t":"うままにならぬものもなければ、またなにひとつ"},{"b":"不足","f":"ふそく"},{"t":"というものもないにつけて、どうかしてでき"},{"b":"得","f":"う"},{"t":"ることなら、いつまでも"},{"b":"死","f":"し"},{"t":"なずに、千"},{"b":"年","f":"ねん"},{"t":"も"},{"b":"万年","f":"まんねん"},{"t":"もこの"},{"b":"世","f":"よ"},{"t":"に"},{"b":"生","f":"い"},{"t":"きていたいと"},{"b":"思","f":"おも"},{"t":"われました。けれど、"},{"b":"昔","f":"むかし"},{"t":"から百"},{"b":"年","f":"ねん"},{"t":"と"},{"b":"長","f":"なが"},{"t":"くこの"},{"b":"世","f":"よ"},{"t":"の"},{"b":"中","f":"なか"},{"t":"に"},{"b":"生","f":"い"},{"t":"きていたものがありませんので、"},{"b":"天子","f":"てんし"},{"t":"さまはこのことを、ひじょうに"},{"b":"悲","f":"かな"},{"t":"しまれました。"}]},{"k":"p","r":[{"t":"　そこであるとき、"},{"b":"巫女","f":"みこ"},{"t":"を"},{"b":"呼","f":"よ"},{"t":"んで、どうしたら"},{"b":"自分","f":"じぶん"},{"t":"は"},{"b":"長生","f":"ながい"},{"t":"きができるだろうかと"},{"b":"問","f":"と"},{"t":"われたのであります。"},{"b":"巫女","f":"みこ"},{"t":"は"},{"b":"秘術","f":"ひじゅつ"},{"t":"をつくして"},{"b":"天","f":"てん"},{"t":"の"},{"b":"神","f":"かみ"},{"t":"さまにうかがいをたてました。そしていいましたのには、これから"},{"b":"海","f":"うみ"},{"t":"を"},{"b":"越","f":"こ"},{"t":"えて"},{"b":"東","f":"ひがし"},{"t":"にゆくと"},{"b":"国","f":"くに"},{"t":"がある。その"},{"b":"国","f":"くに"},{"t":"の"},{"b":"北","f":"きた"},{"t":"の"},{"b":"方","f":"ほう"},{"t":"に"},{"b":"金峰仙","f":"きんぷせん"},{"t":"という"},{"b":"高","f":"たか"},{"t":"い"},{"b":"山","f":"やま"},{"t":"がある。その"},{"b":"山","f":"やま"},{"t":"の"},{"b":"嶺","f":"みね"},{"t":"のところに、"},{"b":"自然","f":"しぜん"},{"t":"の"},{"b":"岩","f":"いわ"},{"t":"でできた"},{"b":"盃","f":"さかずき"},{"t":"がある。その"},{"b":"盃","f":"さかずき"},{"t":"は"},{"b":"天","f":"てん"},{"t":"に"},{"b":"向","f":"む"},{"t":"いてささげられてある。"},{"b":"星","f":"ほし"},{"t":"が"},{"b":"夜々","f":"よるよる"},{"t":"にその"},{"b":"山","f":"やま"},{"t":"の"},{"b":"嶺","f":"みね"},{"t":"を"},{"b":"通","f":"とお"},{"t":"るときに、一"},{"b":"滴","f":"てき"},{"t":"の"},{"b":"露","f":"つゆ"},{"t":"を"},{"b":"落","f":"お"},{"t":"としてゆく。その"},{"b":"露","f":"つゆ"},{"t":"が千"},{"b":"年","f":"ねん"},{"t":"、"},{"b":"万年","f":"まんねん"},{"t":"と、その"},{"b":"盃","f":"さかずき"},{"t":"の"},{"b":"中","f":"なか"},{"t":"にたたえられている。この"},{"b":"清","f":"きよ"},{"t":"らかな"},{"b":"水","f":"みず"},{"t":"を"},{"b":"飲","f":"の"},{"t":"むものは、けっして"},{"b":"死","f":"し"},{"t":"なない。それは"},{"b":"世","f":"よ"},{"t":"にもまれな、すなわち"},{"b":"不死","f":"ふし"},{"t":"の"},{"b":"薬","f":"くすり"},{"t":"である。これをめしあがれば、けっして"},{"b":"死","f":"し"},{"t":"ということはないと、"},{"b":"天子","f":"てんし"},{"t":"さまに"},{"b":"申","f":"もう"},{"t":"しあげたのでありました。"}]},{"k":"blank"},{"k":"h","level":2,"r":[{"t":"二"}]},{"k":"blank"},{"k":"p","r":[{"t":"「"},{"b":"君","f":"きみ"},{"t":"！　"},{"b":"金峰仙","f":"きんぷせん"},{"t":"って、あの"},{"b":"山","f":"やま"},{"t":"かい。」"}]},{"k":"p","r":[{"t":"といって"},{"b":"乙","f":"おつ"},{"t":"は、あちらに"},{"b":"見","f":"み"},{"t":"える"},{"b":"山","f":"やま"},{"t":"の"},{"b":"方","f":"ほう"},{"t":"を"},{"b":"指","f":"さ"},{"t":"して"},{"b":"丙","f":"へい"},{"t":"に"},{"b":"問","f":"と"},{"t":"いました。"}]},{"k":"p","r":[{"t":"「ああ、あの"},{"b":"山","f":"やま"},{"t":"だって、"},{"b":"死","f":"し"},{"t":"んだおじいさんがいったよ。」"}]},{"k":"p","r":[{"t":"と"},{"b":"丙","f":"へい"},{"t":"が"},{"b":"答","f":"こた"},{"t":"えました。"}]},{"k":"p","r":[{"t":"「"},{"b":"君","f":"きみ"},{"t":"はその"},{"b":"話","f":"はなし"},{"t":"をおじいさんから"},{"b":"聞","f":"き"},{"t":"いたのかい。」"}]},{"k":"p","r":[{"t":"と"},{"b":"甲","f":"こう"},{"t":"が"},{"b":"問","f":"と"},{"t":"いました。"}]},{"k":"p","r":[{"t":"「ああ。」"}]},{"k":"p","r":[{"t":"と、"},{"b":"丙","f":"へい"},{"t":"は"},{"b":"軽","f":"かる"},{"t":"くそれに"},{"b":"答","f":"こた"},{"t":"えて、また"},{"b":"話","f":"はなし"},{"t":"を"},{"b":"続","f":"つづ"},{"t":"けました。"}]},{"k":"p","r":[{"t":"　"},{"b":"天子","f":"てんし"},{"t":"さまは"},{"b":"家来","f":"けらい"},{"t":"をお"},{"b":"集","f":"あつ"},{"t":"めになって、だれかその"},{"b":"薬","f":"くすり"},{"t":"を"},{"b":"取","f":"と"},{"t":"ってきてくれるものはないかと"},{"b":"申","f":"もう"},{"t":"されました。みなのものは"},{"b":"顔","f":"かお"},{"t":"を"},{"b":"見合","f":"みあ"},{"t":"わして"},{"b":"容易","f":"ようい"},{"t":"にそれをお"},{"b":"受","f":"う"},{"t":"けいたすものがありません。するとその"},{"b":"中","f":"なか"},{"t":"に"},{"b":"一人","f":"ひとり"},{"t":"の"},{"b":"年老","f":"としと"},{"t":"った"},{"b":"家来","f":"けらい"},{"t":"がありまして、"},{"b":"私","f":"わたくし"},{"t":"がまいりますと"},{"b":"申","f":"もう"},{"t":"し"},{"b":"出","f":"で"},{"t":"ました。"},{"b":"天子","f":"てんし"},{"t":"さまは、"},{"b":"日","f":"ひ"},{"t":"ごろから"},{"b":"忠義","f":"ちゅうぎ"},{"t":"の"},{"b":"家来","f":"けらい"},{"t":"でありましたから、そんなら"},{"b":"汝","f":"なんじ"},{"t":"にその"},{"b":"不死","f":"ふし"},{"t":"の"},{"b":"薬","f":"くすり"},{"t":"を"},{"b":"取","f":"と"},{"t":"りにゆくことを"},{"b":"命","f":"めい"},{"t":"ずるから、"},{"b":"汝","f":"なんじ"},{"t":"は"},{"b":"東","f":"ひがし"},{"t":"の"},{"b":"方","f":"ほう"},{"t":"の"},{"b":"海","f":"うみ"},{"t":"を"},{"b":"渡","f":"わた"},{"t":"って、"},{"b":"絶海","f":"ぜっかい"},{"t":"の"},{"b":"孤島","f":"ことう"},{"t":"にゆき、その"},{"b":"国","f":"くに"},{"t":"の"},{"b":"北方","f":"ほっぽう"},{"t":"にある"},{"b":"金峰仙","f":"きんぷせん"},{"t":"に"},{"b":"登","f":"のぼ"},{"t":"って、"},{"b":"不死","f":"ふし"},{"t":"の"},{"b":"薬","f":"くすり"},{"t":"を"},{"b":"取","f":"と"},{"t":"り、つつがなく"},{"b":"帰","f":"かえ"},{"t":"ってくるようにと、くれぐれもいわれました。"}]},{"k":"p","r":[{"t":"　その"},{"b":"老臣","f":"ろうしん"},{"t":"は、"},{"b":"謹","f":"つつし"},{"t":"んで"},{"b":"天子","f":"てんし"},{"t":"さまの"},{"b":"命","f":"めい"},{"t":"を"},{"b":"奉","f":"ほう"},{"t":"じて、"},{"b":"御前","f":"ごぜん"},{"t":"をさがり、"},{"b":"妻子","f":"さいし"},{"t":"・"},{"b":"親族","f":"しんぞく"},{"t":"・"},{"b":"友人","f":"ゆうじん"},{"t":"らに"},{"b":"別","f":"わか"},{"t":"れを"},{"b":"告","f":"つ"},{"t":"げて、"},{"b":"船","f":"ふね"},{"t":"に"},{"b":"乗","f":"の"},{"t":"って、"},{"b":"東","f":"ひがし"},{"t":"を"},{"b":"指","f":"さ"},{"t":"して"},{"b":"旅立","f":"たびだ"},{"t":"ちいたしましたのであります。その"},{"b":"時分","f":"じぶん"},{"t":"には、まだ"},{"b":"汽船","f":"きせん"},{"t":"などというものがなかったので、"},{"b":"風","f":"かぜ"},{"t":"のまにまに"},{"b":"波","f":"なみ"},{"t":"の"},{"b":"上","f":"うえ"},{"t":"を"},{"b":"漂","f":"ただよ"},{"t":"って、"},{"b":"夜","f":"よる"},{"t":"も"},{"b":"昼","f":"ひる"},{"t":"も"},{"b":"東","f":"ひがし"},{"t":"を"},{"b":"指","f":"さ"},{"t":"してきたのでありました。"}]},{"k":"p","r":[{"t":"　"},{"b":"老臣","f":"ろうしん"},{"t":"は"},{"b":"船","f":"ふね"},{"t":"の"},{"b":"上","f":"うえ"},{"t":"で、"},{"b":"夜","f":"よる"},{"t":"になれば"},{"b":"空","f":"そら"},{"t":"の"},{"b":"星影","f":"ほしかげ"},{"t":"を"},{"b":"仰","f":"あお"},{"t":"いで"},{"b":"船","f":"ふね"},{"t":"のゆくえを"},{"b":"知","f":"し"},{"t":"り、また"},{"b":"朝","f":"あさ"},{"t":"になれば"},{"b":"太陽","f":"たいよう"},{"t":"の"},{"b":"上","f":"のぼ"},{"t":"るのを"},{"b":"見","f":"み"},{"t":"てわずかに"},{"b":"東西南北","f":"とうざいなんぼく"},{"t":"をわきまえたのであります。そのほかはなにひとつ"},{"b":"目","f":"め"},{"t":"に"},{"b":"止","f":"と"},{"t":"まるものもなく、どこを"},{"b":"見","f":"み"},{"t":"ても、ただ"},{"b":"茫々","f":"ぼうぼう"},{"t":"とした"},{"b":"青海原","f":"あおうなばら"},{"t":"でありました。あるときは"},{"b":"風","f":"かぜ"},{"t":"のために"},{"b":"思","f":"おも"},{"t":"わぬ"},{"b":"方向","f":"ほうこう"},{"t":"へ"},{"b":"船","f":"ふね"},{"t":"が"},{"b":"吹","f":"ふ"},{"t":"き"},{"b":"流","f":"なが"},{"t":"され、あるときは"},{"b":"波","f":"なみ"},{"t":"に"},{"b":"揺","f":"ゆ"},{"t":"られて"},{"b":"危","f":"あや"},{"t":"うく"},{"b":"命","f":"いのち"},{"t":"を"},{"b":"助","f":"たす"},{"t":"かり、"},{"b":"幾月","f":"いくつき"},{"t":"も"},{"b":"幾月","f":"いくつき"},{"t":"も"},{"b":"海","f":"うみ"},{"t":"の"},{"b":"上","f":"うえ"},{"t":"に"},{"b":"漂","f":"ただよ"},{"t":"っていましたが、ついにある"},{"b":"日","f":"ひ"},{"t":"のこと、はるかの"},{"b":"波間","f":"なみま"},{"t":"に"},{"b":"島","f":"しま"},{"t":"が"},{"b":"見","f":"み"},{"t":"えたので"},{"b":"大","f":"おお"},{"t":"いに"},{"b":"喜","f":"よろこ"},{"t":"び、"},{"b":"心","f":"こころ"},{"t":"を"},{"b":"励","f":"はげ"},{"t":"ましました。"}]},{"k":"p","r":[{"t":"　その"},{"b":"家来","f":"けらい"},{"t":"は"},{"b":"島","f":"しま"},{"t":"に"},{"b":"上","f":"あ"},{"t":"がりますと、"},{"b":"思","f":"おも"},{"t":"ったよりも"},{"b":"広","f":"ひろ"},{"t":"い"},{"b":"国","f":"くに"},{"t":"でありました。そこでその"},{"b":"国","f":"くに"},{"t":"の"},{"b":"人","f":"ひと"},{"t":"に"},{"b":"向","f":"む"},{"t":"かって"},{"b":"金峰仙","f":"きんぷせん"},{"t":"という"},{"b":"山","f":"やま"},{"t":"はどこにあるかといって"},{"b":"尋","f":"たず"},{"t":"ねましたけれど、だれひとりとして"},{"b":"知","f":"し"},{"t":"っているものがなかったのです。"}]},{"k":"p","r":[{"t":"　その"},{"b":"時分","f":"じぶん"},{"t":"は"},{"b":"大昔","f":"おおむかし"},{"t":"のことで、まだこの"},{"b":"辺","f":"あた"},{"t":"りにはあまり"},{"b":"住","f":"す"},{"t":"んでいるものもなく、"},{"b":"路","f":"みち"},{"t":"も"},{"b":"開","f":"ひら"},{"t":"けていなかったのでありました。"},{"b":"家来","f":"けらい"},{"t":"は"},{"b":"幾年","f":"いくねん"},{"t":"となくその"},{"b":"国","f":"くに"},{"t":"じゅうを"},{"b":"探","f":"さが"},{"t":"して"},{"b":"歩","f":"ある"},{"t":"きました。そして、ついにこの"},{"b":"国","f":"くに"},{"t":"にきて、"},{"b":"金峰仙","f":"きんぷせん"},{"t":"という"},{"b":"山","f":"やま"},{"t":"のあることを"},{"b":"聞","f":"き"},{"t":"いて、"},{"b":"艱難","f":"かんなん"},{"t":"を"},{"b":"冒","f":"おか"},{"t":"して、その"},{"b":"山","f":"やま"},{"t":"にのぼりました。"}]},{"k":"p","r":[{"t":"「そんな"},{"b":"年老","f":"としと"},{"t":"った"},{"b":"家来","f":"けらい"},{"t":"が、どうしてあんな"},{"b":"高","f":"たか"},{"t":"い"},{"b":"山","f":"やま"},{"t":"にのぼったのだい。」"}]},{"k":"p","r":[{"t":"と"},{"b":"甲","f":"こう"},{"t":"が"},{"b":"不思議","f":"ふしぎ"},{"t":"そうにして"},{"b":"丙","f":"へい"},{"t":"に"},{"b":"問","f":"と"},{"t":"いました。"}]},{"k":"p","r":[{"t":"「ほんとうに、あの"},{"b":"山","f":"やま"},{"t":"へはだれも"},{"b":"上","f":"のぼ"},{"t":"れたものがないというよ。」"}]},{"k":"p","r":[{"t":"と"},{"b":"乙","f":"おつ"},{"t":"は"},{"b":"声","f":"こえ"},{"t":"をそろえていいました。"}]},{"k":"p","r":[{"t":"「いつであったか、"},{"b":"探検隊","f":"たんけんたい"},{"t":"が"},{"b":"登","f":"のぼ"},{"t":"って、そのうちで"},{"b":"落","f":"お"},{"t":"ちて"},{"b":"死","f":"し"},{"t":"んだものがあったろう。それからだれも"},{"b":"登","f":"のぼ"},{"t":"ったものがないだろう。」"}]},{"k":"p","r":[{"t":"と"},{"b":"甲","f":"こう"},{"t":"がいいました。"}]},{"k":"p","r":[{"t":"「だけれど、その"},{"b":"家来","f":"けらい"},{"t":"はいっしょうけんめいになって、"},{"b":"登","f":"のぼ"},{"t":"ったんだって、おじいさんがいったよ。」"}]},{"k":"p","r":[{"t":"と"},{"b":"丙","f":"へい"},{"t":"がいいました。"}]},{"k":"p","r":[{"t":"「そうかい。それからどうなったい。」"}]},{"k":"p","r":[{"t":"と"},{"b":"熱心","f":"ねっしん"},{"t":"に"},{"b":"乙","f":"おつ"},{"t":"と"},{"b":"甲","f":"こう"},{"t":"の"},{"b":"二人","f":"ふたり"},{"t":"が"},{"b":"問","f":"と"},{"t":"いました。"},{"b":"丙","f":"へい"},{"t":"はまた"},{"b":"語","f":"かた"},{"t":"り"},{"b":"続","f":"つづ"},{"t":"けました。"}]},{"k":"p","r":[{"t":"　"},{"b":"山","f":"やま"},{"t":"へ"},{"b":"登","f":"のぼ"},{"t":"ると、"},{"b":"巫女","f":"みこ"},{"t":"がいったように"},{"b":"石","f":"いし"},{"t":"の"},{"b":"盃","f":"さかずき"},{"t":"がありました。そしてその"},{"b":"中","f":"なか"},{"t":"に"},{"b":"清","f":"きよ"},{"t":"らかな"},{"b":"水","f":"みず"},{"t":"がたまっていました。"},{"b":"家来","f":"けらい"},{"t":"は"},{"b":"携","f":"たずさ"},{"t":"えてきた"},{"b":"小","f":"ちい"},{"t":"さな"},{"b":"徳利","f":"とくり"},{"t":"の"},{"b":"中","f":"なか"},{"t":"にその"},{"b":"水","f":"みず"},{"t":"を"},{"b":"入","f":"い"},{"t":"れました。そして"},{"b":"早","f":"はや"},{"t":"くこれを"},{"b":"携","f":"たずさ"},{"t":"えて、"},{"b":"国","f":"くに"},{"t":"へもどって"},{"b":"天子","f":"てんし"},{"t":"さまにさしあげようと"},{"b":"思","f":"おも"},{"t":"って、"},{"b":"山","f":"やま"},{"t":"を"},{"b":"下","f":"くだ"},{"t":"りました。"}]},{"k":"p","r":[{"t":"　"},{"b":"家来","f":"けらい"},{"t":"は"},{"b":"山","f":"やま"},{"t":"を"},{"b":"下","f":"くだ"},{"t":"って、"},{"b":"海辺","f":"うみべ"},{"t":"へきて、"},{"b":"毎日","f":"まいにち"},{"t":"その"},{"b":"海岸","f":"かいがん"},{"t":"を"},{"b":"通","f":"とお"},{"t":"る"},{"b":"船","f":"ふね"},{"t":"を"},{"b":"見","f":"み"},{"t":"ていたのであります。けれど、一そうも"},{"b":"目","f":"め"},{"t":"にとまりません。"},{"b":"毎日","f":"まいにち"},{"t":"、"},{"b":"毎日","f":"まいにち"},{"t":"、"},{"b":"沖","f":"おき"},{"t":"の"},{"b":"方","f":"ほう"},{"t":"を"},{"b":"見","f":"み"},{"t":"ては、"},{"b":"通","f":"とお"},{"t":"る"},{"b":"船","f":"ふね"},{"t":"を"},{"b":"見","f":"み"},{"t":"ていますうちに、そのかいもなく、ふと"},{"b":"病","f":"やまい"},{"t":"にかかって、それがもとになって、"},{"b":"遠","f":"とお"},{"t":"い"},{"b":"異郷","f":"いきょう"},{"t":"の"},{"b":"空","f":"そら"},{"t":"でついに"},{"b":"死","f":"な"},{"t":"くなってしまいました。"}]},{"k":"blank"},{"k":"h","level":2,"r":[{"t":"三"}]},{"k":"blank"},{"k":"p","r":[{"t":"「それからどうなったい。」"}]},{"k":"p","r":[{"t":"と、"},{"b":"甲","f":"こう"},{"t":"が"},{"b":"丙","f":"へい"},{"t":"に"},{"b":"尋","f":"たず"},{"t":"ねました。"}]},{"k":"p","r":[{"t":"「これで、もうお"},{"b":"話","f":"はなし"},{"t":"は"},{"b":"終","f":"お"},{"t":"わったんだよ。」"}]},{"k":"p","r":[{"t":"　"},{"b":"丙","f":"へい"},{"t":"が"},{"b":"星晴","f":"ほしば"},{"t":"れのした"},{"b":"空","f":"そら"},{"t":"をながめて"},{"b":"答","f":"こた"},{"t":"えました。"}]},{"k":"p","r":[{"t":"「その"},{"b":"家来","f":"けらい"},{"t":"は"},{"b":"死","f":"し"},{"t":"んでしまったから、"},{"b":"天子","f":"てんし"},{"t":"さまも"},{"b":"死","f":"し"},{"t":"んでしまったんだね。」"}]},{"k":"p","r":[{"t":"と"},{"b":"乙","f":"おつ"},{"t":"がいいました。"}]},{"k":"p","r":[{"t":"「それはそうさ、"},{"b":"天子","f":"てんし"},{"t":"さまも"},{"b":"不死","f":"ふし"},{"t":"の"},{"b":"薬","f":"くすり"},{"t":"を"},{"b":"飲","f":"の"},{"t":"むことができなかったから、やはり"},{"b":"年","f":"とし"},{"t":"を"},{"b":"老","f":"と"},{"t":"って"},{"b":"死","f":"し"},{"t":"んでしまいなされたろう。」"}]},{"k":"p","r":[{"t":"と"},{"b":"丙","f":"へい"},{"t":"がいいました。"}]},{"k":"p","r":[{"t":"「ばかだね、その"},{"b":"家来","f":"けらい"},{"t":"は"},{"b":"自分","f":"じぶん"},{"t":"もその"},{"b":"薬","f":"くすり"},{"t":"を"},{"b":"飲","f":"の"},{"t":"んで、そして"},{"b":"天子","f":"てんし"},{"t":"さまへも"},{"b":"徳利","f":"とくり"},{"t":"の"},{"b":"中","f":"なか"},{"t":"へ"},{"b":"入","f":"い"},{"t":"れて"},{"b":"持","f":"も"},{"t":"ってゆけばよかったのに。そうすれば"},{"b":"二人","f":"ふたり"},{"t":"とも"},{"b":"死","f":"し"},{"t":"ななかったろうに。」"}]},{"k":"p","r":[{"t":"と、"},{"b":"乙","f":"おつ"},{"t":"が"},{"b":"考","f":"かんが"},{"t":"えながら"},{"b":"家来","f":"けらい"},{"t":"の"},{"b":"智慧","f":"ちえ"},{"t":"のないのを"},{"b":"笑","f":"わら"},{"t":"っていいました。"}]},{"k":"p","r":[{"t":"「だって、"},{"b":"天子","f":"てんし"},{"t":"さまより"},{"b":"先","f":"さき"},{"t":"に"},{"b":"飲","f":"の"},{"t":"むのは"},{"b":"不忠","f":"ふちゅう"},{"t":"と"},{"b":"思","f":"おも"},{"t":"ったかもしれないさ。」"}]},{"k":"p","r":[{"t":"と"},{"b":"甲","f":"こう"},{"t":"がいいました。"}]},{"k":"p","r":[{"t":"　三"},{"b":"人","f":"にん"},{"t":"は、かしの"},{"b":"木","f":"き"},{"t":"の"},{"b":"下","f":"した"},{"t":"に"},{"b":"腰","f":"こし"},{"t":"を"},{"b":"下","f":"お"},{"t":"ろして、"},{"b":"西南","f":"せいなん"},{"t":"の"},{"b":"国境","f":"くにざかい"},{"t":"にある"},{"b":"金峰仙","f":"きんぷせん"},{"t":"の"},{"b":"方","f":"ほう"},{"t":"を"},{"b":"見","f":"み"},{"t":"ながら、まだあの"},{"b":"高","f":"たか"},{"t":"い"},{"b":"山","f":"やま"},{"t":"の"},{"b":"嶺","f":"みね"},{"t":"には"},{"b":"不死","f":"ふし"},{"t":"の"},{"b":"泉","f":"いずみ"},{"t":"があるだろうかというようなことを"},{"b":"話","f":"はな"},{"t":"して"},{"b":"空想","f":"くうそう"},{"t":"にふけりました。"},{"b":"星晴","f":"ほしば"},{"t":"れのした"},{"b":"夜","f":"よる"},{"t":"の"},{"b":"空","f":"そら"},{"t":"に"},{"b":"高","f":"たか"},{"t":"い"},{"b":"山","f":"やま"},{"t":"のとがった"},{"b":"嶺","f":"みね"},{"t":"が"},{"b":"黒","f":"くろ"},{"t":"くそびえて"},{"b":"見","f":"み"},{"t":"えます。その"},{"b":"嶺","f":"みね"},{"t":"の"},{"b":"上","f":"うえ"},{"t":"にあたって一つ"},{"b":"金色","f":"こんじき"},{"t":"の"},{"b":"星","f":"ほし"},{"t":"がキラキラと"},{"b":"輝","f":"かがや"},{"t":"いています。"}]},{"k":"p","r":[{"t":"　三"},{"b":"人","f":"にん"},{"t":"の"},{"b":"子供","f":"こども"},{"t":"らは、よく"},{"b":"祖母","f":"そぼ"},{"t":"や、"},{"b":"母親","f":"ははおや"},{"t":"から、"},{"b":"夜","f":"よ"},{"t":"ごとに"},{"b":"天","f":"てん"},{"t":"からろうそくが"},{"b":"降","f":"ふ"},{"t":"ってくるとか、また"},{"b":"下界","f":"げかい"},{"t":"で、この"},{"b":"山","f":"やま"},{"t":"の"},{"b":"神","f":"かみ"},{"t":"さまに"},{"b":"祈","f":"いの"},{"t":"りをささげるろうそくの"},{"b":"火","f":"ひ"},{"t":"が、"},{"b":"空","f":"そら"},{"t":"を"},{"b":"泳","f":"およ"},{"t":"いで"},{"b":"山","f":"やま"},{"t":"の"},{"b":"嶺","f":"みね"},{"t":"に"},{"b":"上","f":"のぼ"},{"t":"るとかいうような"},{"b":"不思議","f":"ふしぎ"},{"t":"な"},{"b":"話","f":"はなし"},{"t":"を"},{"b":"胸","f":"むね"},{"t":"の"},{"b":"中","f":"うち"},{"t":"に"},{"b":"思","f":"おも"},{"t":"い"},{"b":"出","f":"だ"},{"t":"しました。"}]},{"k":"p","r":[{"t":"「"},{"b":"神","f":"かみ"},{"t":"さまというものはあるものだろうか。」"}]},{"k":"p","r":[{"t":"と、もっとも"},{"b":"年少","f":"ねんしょう"},{"t":"の"},{"b":"丙","f":"へい"},{"t":"が、たまらなくなってため"},{"b":"息","f":"いき"},{"t":"をしながらいいました。"}]},{"k":"p","r":[{"t":"「"},{"b":"学校","f":"がっこう"},{"t":"の"},{"b":"先生","f":"せんせい"},{"t":"はないといったよ。」"}]},{"k":"p","r":[{"t":"と、"},{"b":"乙","f":"おつ"},{"t":"が"},{"b":"教師","f":"きょうし"},{"t":"のいったことを"},{"b":"思","f":"おも"},{"t":"い"},{"b":"出","f":"だ"},{"t":"していいました。"}]},{"k":"p","r":[{"t":"「"},{"b":"先生","f":"せんせい"},{"t":"はどうして、ないことを"},{"b":"知","f":"し"},{"t":"っているだろう。」"}]},{"k":"p","r":[{"t":"と、"},{"b":"甲","f":"こう"},{"t":"が"},{"b":"乙","f":"おつ"},{"t":"のいったことに"},{"b":"疑","f":"うたが"},{"t":"いをはさみました。"}]},{"k":"p","r":[{"t":"「"},{"b":"僕","f":"ぼく"},{"t":"はあると"},{"b":"思","f":"おも"},{"t":"うよ。そんなら、だれがあの"},{"b":"星","f":"ほし"},{"t":"や、"},{"b":"山","f":"やま"},{"t":"や、この"},{"b":"地球","f":"ちきゅう"},{"t":"や、"},{"b":"人間","f":"にんげん"},{"t":"を"},{"b":"造","f":"つく"},{"t":"ったのだろう。」"}]},{"k":"p","r":[{"t":"と、"},{"b":"丙","f":"へい"},{"t":"が"},{"b":"輝","f":"かがや"},{"t":"く"},{"b":"瞳","f":"ひとみ"},{"t":"を"},{"b":"星","f":"ほし"},{"t":"に"},{"b":"向","f":"む"},{"t":"けて"},{"b":"涙","f":"なみだ"},{"t":"ぐみました。"},{"b":"夜","f":"よる"},{"t":"の"},{"b":"風","f":"かぜ"},{"t":"に"},{"b":"吹","f":"ふ"},{"t":"かれて、かしの"},{"b":"木","f":"き"},{"t":"がサワサワと"},{"b":"鳴","f":"な"},{"t":"っています。"}]},{"k":"p","r":[{"t":"「そして、だれがこの"},{"b":"人間","f":"にんげん"},{"t":"を"},{"b":"造","f":"つく"},{"t":"ったんだろう。」"}]},{"k":"p","r":[{"t":"と、"},{"b":"丙","f":"へい"},{"t":"が"},{"b":"声","f":"こえ"},{"t":"を"},{"b":"慄","f":"ふる"},{"t":"わせて"},{"b":"叫","f":"さけ"},{"t":"びました。"}]},{"k":"p","r":[{"t":"　三"},{"b":"人","f":"にん"},{"t":"はしばらく"},{"b":"黙","f":"だま"},{"t":"って、"},{"b":"深","f":"ふか"},{"t":"く"},{"b":"思","f":"おも"},{"t":"いに"},{"b":"沈","f":"しず"},{"t":"んでいましたが、"}]},{"k":"p","r":[{"t":"「"},{"b":"不思議","f":"ふしぎ"},{"t":"だ。」"}]},{"k":"p","r":[{"t":"といい"},{"b":"合","f":"あ"},{"t":"いました。"}]},{"k":"p","r":[{"t":"　すでに"},{"b":"北国","f":"ほっこく"},{"t":"の"},{"b":"夏","f":"なつ"},{"t":"の"},{"b":"夜","f":"よ"},{"t":"はふけてみえました。"}]}]}