{"id":"050979","title":"星の世界から","author":"小川未明","authorId":"001475","blocks":[{"k":"h","level":2,"r":[{"t":"一"}]},{"k":"blank"},{"k":"p","r":[{"t":"　"},{"b":"良吉","f":"りょうきち"},{"t":"は"},{"b":"貧","f":"まず"},{"t":"しい"},{"b":"家","f":"いえ"},{"t":"に"},{"b":"生","f":"う"},{"t":"まれました。その"},{"b":"村","f":"むら"},{"t":"は"},{"b":"寂","f":"さび"},{"t":"しい、"},{"b":"森","f":"もり"},{"t":"のたくさんある"},{"b":"村","f":"むら"},{"t":"でありました。"},{"b":"小鳥","f":"ことり"},{"t":"がきてさえずります。また"},{"b":"春","f":"はる"},{"t":"になると、"},{"b":"白","f":"しろ"},{"t":"い"},{"b":"花","f":"はな"},{"t":"や、"},{"b":"香","f":"かお"},{"t":"りの"},{"b":"高","f":"たか"},{"t":"い、いろいろの"},{"b":"花","f":"はな"},{"t":"が"},{"b":"咲","f":"さ"},{"t":"きました。"}]},{"k":"p","r":[{"t":"　"},{"b":"良吉","f":"りょうきち"},{"t":"には"},{"b":"仲","f":"なか"},{"t":"のいい"},{"b":"文雄","f":"ふみお"},{"t":"という"},{"b":"同","f":"おな"},{"t":"じ"},{"b":"年","f":"とし"},{"t":"ごろの"},{"b":"友","f":"とも"},{"t":"だちがありました。"},{"b":"二人","f":"ふたり"},{"t":"はいつもいっしょに"},{"b":"棒","f":"ぼう"},{"t":"を"},{"b":"持","f":"も"},{"t":"ったり、"},{"b":"駆","f":"か"},{"t":"けっこをしたり、また、さおを"},{"b":"持","f":"も"},{"t":"って"},{"b":"河","f":"かわ"},{"t":"にいったりして、"},{"b":"仲","f":"なか"},{"t":"よく"},{"b":"遊","f":"あそ"},{"t":"びました。"}]},{"k":"p","r":[{"t":"　"},{"b":"村","f":"むら"},{"t":"はずれには"},{"b":"河","f":"かわ"},{"t":"が"},{"b":"流","f":"なが"},{"t":"れていました。その"},{"b":"水","f":"みず"},{"t":"はたくさんできれいでありました。"},{"b":"河","f":"かわ"},{"t":"のほとりには"},{"b":"草","f":"くさ"},{"t":"が"},{"b":"茂","f":"しげ"},{"t":"っていました。"},{"b":"二人","f":"ふたり"},{"t":"はその"},{"b":"草","f":"くさ"},{"t":"の"},{"b":"上","f":"うえ"},{"t":"に"},{"b":"腰","f":"こし"},{"t":"を"},{"b":"下","f":"お"},{"t":"ろして、"},{"b":"水","f":"みず"},{"t":"を"},{"b":"見","f":"み"},{"t":"つめながら"},{"b":"釣","f":"つ"},{"t":"りをいたしました。"}]},{"k":"p","r":[{"t":"　また"},{"b":"風","f":"かぜ"},{"t":"の"},{"b":"吹","f":"ふ"},{"t":"く"},{"b":"日","f":"ひ"},{"t":"には、いっしょにくりの"},{"b":"実","f":"み"},{"t":"を"},{"b":"拾","f":"ひろ"},{"t":"って"},{"b":"歩","f":"ある"},{"t":"きました。また"},{"b":"枯","f":"か"},{"t":"れ"},{"b":"枝","f":"えだ"},{"t":"などを"},{"b":"拾","f":"ひろ"},{"t":"ってきて、"},{"b":"親","f":"おや"},{"t":"の"},{"b":"手助","f":"てだす"},{"t":"けなどをいたしたこともありました。こうして"},{"b":"二人","f":"ふたり"},{"t":"は、なんでも"},{"b":"持","f":"も"},{"t":"っているものは、たがいに"},{"b":"貸","f":"か"},{"t":"し"},{"b":"合","f":"あ"},{"t":"って"},{"b":"仲","f":"なか"},{"t":"よく"},{"b":"遊","f":"あそ"},{"t":"びました。たまに"},{"b":"両親","f":"りょうしん"},{"t":"が"},{"b":"町","f":"まち"},{"t":"へいって"},{"b":"買","f":"か"},{"t":"ってきてくれた"},{"b":"絵草紙","f":"えぞうし"},{"t":"や、おもちゃなどがあると、それを"},{"b":"良吉","f":"りょうきち"},{"t":"は"},{"b":"文雄","f":"ふみお"},{"t":"にも"},{"b":"見","f":"み"},{"t":"せてやったり、"},{"b":"貸","f":"か"},{"t":"してやったりいたしました。また、"},{"b":"文雄","f":"ふみお"},{"t":"も"},{"b":"同","f":"おな"},{"t":"じことで、なにか"},{"b":"珍","f":"めずら"},{"t":"しいものが"},{"b":"手","f":"て"},{"t":"に"},{"b":"入","f":"はい"},{"t":"ると、きっとそれを"},{"b":"良吉","f":"りょうきち"},{"t":"のところへ"},{"b":"持","f":"も"},{"t":"ってきて"},{"b":"見","f":"み"},{"t":"せました。"},{"b":"二人","f":"ふたり"},{"t":"の"},{"b":"間","f":"あいだ"},{"t":"では、なんでも"},{"b":"差別","f":"さべつ"},{"t":"なくして"},{"b":"仲","f":"なか"},{"t":"よく"},{"b":"遊","f":"あそ"},{"t":"びました。だから、その"},{"b":"村","f":"むら"},{"t":"は"},{"b":"町","f":"まち"},{"t":"から"},{"b":"遠","f":"とお"},{"t":"くはなれていて、さびしい"},{"b":"村","f":"むら"},{"t":"でありましたけれど、"},{"b":"二人","f":"ふたり"},{"t":"はけっしてさびしいとは"},{"b":"思","f":"おも"},{"t":"いませんでした。"},{"b":"二人","f":"ふたり"},{"t":"はいつも、"},{"b":"楽","f":"たの"},{"t":"しく"},{"b":"仲","f":"なか"},{"t":"よくして"},{"b":"遊","f":"あそ"},{"t":"んでいました。"}]},{"k":"p","r":[{"t":"　しかし、"},{"b":"不幸","f":"ふこう"},{"t":"というものは、いつ"},{"b":"人間","f":"ひと"},{"t":"の"},{"b":"身","f":"み"},{"t":"の"},{"b":"上","f":"うえ"},{"t":"にやってくるものだかわかりません。ある"},{"b":"寒","f":"さむ"},{"t":"い、もう"},{"b":"秋","f":"あき"},{"t":"も"},{"b":"老","f":"ふ"},{"t":"けてゆくころでありました。"},{"b":"文雄","f":"ふみお"},{"t":"は、ふとしたかぜをひきました。そして、それがだんだん"},{"b":"重","f":"おも"},{"t":"くなって"},{"b":"床","f":"とこ"},{"t":"につきました。"},{"b":"良吉","f":"りょうきち"},{"t":"は"},{"b":"心配","f":"しんぱい"},{"t":"して、"},{"b":"毎日","f":"まいにち"},{"t":"のように"},{"b":"文雄","f":"ふみお"},{"t":"の"},{"b":"家","f":"うち"},{"t":"へいっては、"},{"b":"病気","f":"びょうき"},{"t":"をみまいました。"},{"b":"文雄","f":"ふみお"},{"t":"の"},{"b":"両親","f":"ふたおや"},{"t":"もいっしょうけんめいで"},{"b":"看病","f":"かんびょう"},{"t":"いたしました。けれど、ついに"},{"b":"文雄","f":"ふみお"},{"t":"はなおりませんでした。"},{"b":"枕","f":"まくら"},{"t":"もとにすわって、"},{"b":"心配","f":"しんぱい"},{"t":"そうに"},{"b":"自分","f":"じぶん"},{"t":"の"},{"b":"顔","f":"かお"},{"t":"を"},{"b":"見","f":"み"},{"t":"つめている、"},{"b":"友","f":"とも"},{"t":"だちの"},{"b":"良吉","f":"りょうきち"},{"t":"をじっと"},{"b":"見","f":"み"},{"t":"て、"}]},{"k":"p","r":[{"t":"「"},{"b":"早","f":"はや"},{"t":"くなおって、また"},{"b":"君","f":"きみ"},{"t":"といっしょに"},{"b":"遊","f":"あそ"},{"t":"ぼうね。」"}]},{"k":"p","r":[{"t":"と、"},{"b":"文雄","f":"ふみお"},{"t":"はやつれた"},{"b":"姿","f":"すがた"},{"t":"になりながら、にっこりと"},{"b":"笑","f":"わら"},{"t":"っていいました。"}]},{"k":"p","r":[{"t":"「ああ、"},{"b":"遊","f":"あそ"},{"t":"ぼうよ、"},{"b":"君","f":"きみ"},{"t":"、"},{"b":"気分","f":"きぶん"},{"t":"はちっとはいいかい。」"}]},{"k":"p","r":[{"t":"と、"},{"b":"良吉","f":"りょうきち"},{"t":"は"},{"b":"笑顔","f":"えがお"},{"t":"になって、そのやせた"},{"b":"哀","f":"あわ"},{"t":"れな"},{"b":"友","f":"とも"},{"t":"だちの"},{"b":"手","f":"て"},{"t":"を"},{"b":"握","f":"にぎ"},{"t":"りました。しかし、これが"},{"b":"別","f":"わか"},{"t":"れでありました。とうとう"},{"b":"文雄","f":"ふみお"},{"t":"はその"},{"b":"晩","f":"ばん"},{"b":"死","f":"し"},{"t":"んでしまいました。"}]},{"k":"blank"},{"k":"h","level":2,"r":[{"t":"二"}]},{"k":"blank"},{"k":"p","r":[{"t":"　"},{"b":"良吉","f":"りょうきち"},{"t":"は"},{"b":"悲","f":"かな"},{"t":"しさのあまり"},{"b":"泣","f":"な"},{"t":"きあかしました。"},{"b":"文雄","f":"ふみお"},{"t":"は"},{"b":"村","f":"むら"},{"t":"のお"},{"b":"寺","f":"てら"},{"t":"の"},{"b":"墓地","f":"ぼち"},{"t":"に"},{"b":"葬","f":"ほうむ"},{"t":"られました。"},{"b":"良吉","f":"りょうきち"},{"t":"は"},{"b":"文雄","f":"ふみお"},{"t":"のお"},{"b":"葬式","f":"そうしき"},{"t":"のときにも"},{"b":"泣","f":"な"},{"t":"いてついてゆきました。それからというものは、"},{"b":"彼","f":"かれ"},{"t":"は"},{"b":"毎日","f":"まいにち"},{"t":"のように"},{"b":"暇","f":"ひま"},{"t":"さえあればお"},{"b":"寺","f":"てら"},{"t":"の"},{"b":"墓地","f":"ぼち"},{"t":"へいって、"},{"b":"文雄","f":"ふみお"},{"t":"の"},{"b":"墓","f":"はか"},{"t":"の"},{"b":"前","f":"まえ"},{"t":"にすわって、ちょうど"},{"b":"生","f":"い"},{"t":"きている"},{"b":"友","f":"とも"},{"t":"だちに"},{"b":"向","f":"む"},{"t":"かって"},{"b":"話","f":"はな"},{"t":"すと"},{"b":"同","f":"おな"},{"t":"じように"},{"b":"語","f":"かた"},{"t":"りました。"}]},{"k":"p","r":[{"t":"「"},{"b":"君","f":"きみ"},{"t":"、さびしいだろうと"},{"b":"思","f":"おも"},{"t":"って"},{"b":"僕","f":"ぼく"},{"t":"は"},{"b":"遊","f":"あそ"},{"t":"びにきたよ。」"}]},{"k":"p","r":[{"t":"と、"},{"b":"良吉","f":"りょうきち"},{"t":"はいいました。"},{"b":"木枯","f":"こが"},{"t":"らしは、そのさびしいほかにはだれも"},{"b":"人影","f":"ひとかげ"},{"t":"のいない"},{"b":"墓地","f":"ぼち"},{"t":"に"},{"b":"吹","f":"ふ"},{"t":"きすさんで、"},{"b":"枯","f":"か"},{"t":"れた"},{"b":"葉","f":"は"},{"t":"が、"},{"b":"空","f":"そら"},{"t":"や、"},{"b":"地","f":"ち"},{"t":"の"},{"b":"上","f":"うえ"},{"t":"にわびしくまわっていました。そして、しばらくそこに"},{"b":"良吉","f":"りょうきち"},{"t":"はいますと、やがて"},{"b":"日","f":"ひ"},{"t":"がうす"},{"b":"暗","f":"ぐら"},{"t":"くなります。すると"},{"b":"彼","f":"かれ"},{"t":"は"},{"b":"名残惜","f":"なごりお"},{"t":"しそうに"},{"b":"帰","f":"かえ"},{"t":"ってゆくのでありました。"}]},{"k":"p","r":[{"t":"　けれど、"},{"b":"良吉","f":"りょうきち"},{"t":"の一"},{"b":"家","f":"か"},{"t":"は"},{"b":"事情","f":"じじょう"},{"t":"があって、その"},{"b":"明","f":"あ"},{"t":"くる"},{"b":"年","f":"とし"},{"t":"にこの"},{"b":"村","f":"むら"},{"t":"からほかの"},{"b":"村","f":"むら"},{"t":"へ"},{"b":"移","f":"うつ"},{"t":"らなければならなくなりました。"},{"b":"良吉","f":"りょうきち"},{"t":"はまたしばらく"},{"b":"文雄","f":"ふみお"},{"t":"のお"},{"b":"墓","f":"はか"},{"t":"にもおまいりができなくなると"},{"b":"思","f":"おも"},{"t":"って、ある"},{"b":"日","f":"ひ"},{"t":"のことお"},{"b":"墓","f":"はか"},{"t":"へおまいりに"},{"b":"参","f":"まい"},{"t":"りました。そして、そのわけをいってから、"},{"b":"彼","f":"かれ"},{"t":"は"},{"b":"名残惜","f":"なごりお"},{"t":"しそうについにこの"},{"b":"村","f":"むら"},{"t":"を"},{"b":"離","f":"はな"},{"t":"れたのであります。"}]},{"k":"p","r":[{"t":"　"},{"b":"今度","f":"こんど"},{"t":"、"},{"b":"良吉","f":"りょうきち"},{"t":"の一"},{"b":"家","f":"か"},{"t":"の"},{"b":"越","f":"こ"},{"t":"してきたところは、ある"},{"b":"金持","f":"かねも"},{"t":"ちの"},{"b":"家","f":"いえ"},{"t":"の"},{"b":"隣","f":"となり"},{"t":"でありました。その"},{"b":"金持","f":"かねも"},{"t":"ちの"},{"b":"家","f":"うち"},{"t":"にも、ちょうど"},{"b":"良吉","f":"りょうきち"},{"t":"と"},{"b":"同","f":"おな"},{"t":"じ"},{"b":"年","f":"とし"},{"t":"ごろの"},{"b":"力蔵","f":"りきぞう"},{"t":"という"},{"b":"子供","f":"こども"},{"t":"がありました。そして、"},{"b":"二人","f":"ふたり"},{"t":"はじきに"},{"b":"友","f":"とも"},{"t":"だちとなりました。"}]},{"k":"p","r":[{"t":"　"},{"b":"力蔵","f":"りきぞう"},{"t":"はほしいものは、なんでも"},{"b":"買","f":"か"},{"t":"ってもらいました。"},{"b":"流行","f":"はやり"},{"t":"のおもちゃも、きれいな"},{"b":"本","f":"ほん"},{"t":"も、いろいろのものを"},{"b":"持","f":"も"},{"t":"っていました。そして、それらのものを"},{"b":"家","f":"いえ"},{"t":"の"},{"b":"外","f":"そと"},{"t":"に"},{"b":"持","f":"も"},{"t":"ってきては、"},{"b":"同","f":"おな"},{"t":"じ"},{"b":"年","f":"とし"},{"t":"ごろの"},{"b":"友","f":"とも"},{"t":"だちにみせました。"},{"b":"良吉","f":"りょうきち"},{"t":"にはまだはじめて"},{"b":"見","f":"み"},{"t":"るような、"},{"b":"名","f":"な"},{"t":"も"},{"b":"知","f":"し"},{"t":"らない"},{"b":"珍","f":"めずら"},{"t":"しいおもちゃがありました。けれど"},{"b":"力蔵","f":"りきぞう"},{"t":"はだれにもそれを"},{"b":"貸","f":"か"},{"t":"してくれません。たとえ"},{"b":"貸","f":"か"},{"t":"してくれても、すぐにそれを"},{"b":"取","f":"と"},{"t":"ってしまいました。"}]},{"k":"p","r":[{"t":"　"},{"b":"良吉","f":"りょうきち"},{"t":"も"},{"b":"心","f":"こころ"},{"t":"の"},{"b":"中","f":"うち"},{"t":"で、"},{"b":"自分","f":"じぶん"},{"t":"もあんなおもちゃがほしいものだと"},{"b":"思","f":"おも"},{"t":"いました。"},{"b":"彼","f":"かれ"},{"t":"は"},{"b":"飛行機","f":"ひこうき"},{"t":"や、モーターボートや、オルゴールや、"},{"b":"空気銃","f":"くうきじゅう"},{"t":"などは一つも"},{"b":"持","f":"も"},{"t":"ってみたことがありません。どれでも"},{"b":"力蔵","f":"りきぞう"},{"t":"が"},{"b":"持","f":"も"},{"t":"っているようなおもちゃの一つでも"},{"b":"自分","f":"じぶん"},{"t":"が"},{"b":"持","f":"も"},{"t":"つことができたなら、"},{"b":"自分","f":"じぶん"},{"t":"はどんなにうれしいかしれないと"},{"b":"思","f":"おも"},{"t":"いました。"}]},{"k":"p","r":[{"t":"　"},{"b":"力蔵","f":"りきぞう"},{"t":"が"},{"b":"持","f":"も"},{"t":"っている、いろいろなおもちゃの"},{"b":"中","f":"なか"},{"t":"でも、"},{"b":"彼","f":"かれ"},{"t":"のいちばんほしいと"},{"b":"思","f":"おも"},{"t":"ったものは"},{"b":"飛行機","f":"ひこうき"},{"t":"と、オルゴールでありました。そのオルゴールは、なんともいえないいい"},{"b":"音色","f":"ねいろ"},{"t":"がするのでありました。"}]},{"k":"p","r":[{"t":"「"},{"b":"力蔵","f":"りきぞう"},{"t":"さん、"},{"b":"私","f":"わたし"},{"t":"にすこしその"},{"b":"鳴","f":"な"},{"t":"るおもちゃを"},{"b":"貸","f":"か"},{"t":"してくれない？」"}]},{"k":"p","r":[{"t":"と、"},{"b":"良吉","f":"りょうきち"},{"t":"はある"},{"b":"日","f":"ひ"},{"t":"、"},{"b":"外","f":"そと"},{"t":"で"},{"b":"力蔵","f":"りきぞう"},{"t":"がオルゴールを"},{"b":"鳴","f":"な"},{"t":"らしているそばへいって"},{"b":"頼","f":"たの"},{"t":"みました。すると、"},{"b":"力蔵","f":"りきぞう"},{"t":"は"},{"b":"頭","f":"あたま"},{"t":"を"},{"b":"左右","f":"さゆう"},{"t":"に"},{"b":"振","f":"ふ"},{"t":"って、"}]},{"k":"p","r":[{"t":"「いやだ。これを"},{"b":"貸","f":"か"},{"t":"すと、"},{"b":"君","f":"きみ"},{"t":"はすぐに、"},{"b":"壊","f":"こわ"},{"t":"してしまうもの。」"}]},{"k":"p","r":[{"t":"といいました。"}]},{"k":"p","r":[{"t":"「"},{"b":"大事","f":"だいじ"},{"t":"にして"},{"b":"持","f":"も"},{"t":"っているから、ちっとばかり"},{"b":"貸","f":"か"},{"t":"してくれない？」"}]},{"k":"p","r":[{"t":"と、"},{"b":"良吉","f":"りょうきち"},{"t":"は"},{"b":"目","f":"め"},{"t":"に"},{"b":"涙","f":"なみだ"},{"t":"をたたえて"},{"b":"頼","f":"たの"},{"t":"みました。"}]},{"k":"p","r":[{"t":"「"},{"b":"僕","f":"ぼく"},{"t":"は、"},{"b":"人","f":"ひと"},{"t":"に"},{"b":"貸","f":"か"},{"t":"すのはいやだ。」"}]},{"k":"p","r":[{"t":"といって、"},{"b":"力蔵","f":"りきぞう"},{"t":"は"},{"b":"貸","f":"か"},{"t":"してくれませんでした。"}]},{"k":"blank"},{"k":"h","level":2,"r":[{"t":"三"}]},{"k":"blank"},{"k":"p","r":[{"t":"　"},{"b":"良吉","f":"りょうきち"},{"t":"はしかたがないから、"},{"b":"林","f":"はやし"},{"t":"の"},{"b":"中","f":"なか"},{"t":"に"},{"b":"入","f":"はい"},{"t":"って"},{"b":"竹","f":"たけ"},{"t":"を"},{"b":"切","f":"き"},{"t":"ってきて、"},{"b":"自分","f":"じぶん"},{"t":"でそれに"},{"b":"小","f":"ちい"},{"t":"さな"},{"b":"穴","f":"あな"},{"t":"をあけて"},{"b":"笛","f":"ふえ"},{"t":"を"},{"b":"造","f":"つく"},{"t":"って"},{"b":"吹","f":"ふ"},{"t":"いていました。すると、四"},{"b":"方","f":"ほう"},{"t":"から"},{"b":"小鳥","f":"ことり"},{"t":"がそれを"},{"b":"聞","f":"き"},{"t":"きつけ"},{"b":"集","f":"あつ"},{"t":"まってきて、"},{"b":"近間","f":"ちかま"},{"t":"の"},{"b":"木","f":"き"},{"t":"の"},{"b":"枝","f":"えだ"},{"t":"に"},{"b":"止","f":"と"},{"t":"まってその"},{"b":"笛","f":"ふえ"},{"t":"を"},{"b":"自分","f":"じぶん"},{"t":"らの"},{"b":"友","f":"とも"},{"t":"だちだと"},{"b":"思","f":"おも"},{"t":"っていっしょになってさえずっていました。この"},{"b":"有","f":"あ"},{"t":"り"},{"b":"様","f":"さま"},{"t":"を"},{"b":"見","f":"み"},{"t":"ると"},{"b":"力蔵","f":"りきぞう"},{"t":"はすぐに"},{"b":"良吉","f":"りょうきち"},{"t":"の"},{"b":"持","f":"も"},{"t":"っている"},{"b":"笛","f":"ふえ"},{"t":"が"},{"b":"欲","f":"ほ"},{"t":"しくなりました。"}]},{"k":"p","r":[{"t":"「"},{"b":"君","f":"きみ"},{"t":"にオルゴールを"},{"b":"貸","f":"か"},{"t":"してあげるから、その"},{"b":"笛","f":"ふえ"},{"t":"を"},{"b":"僕","f":"ぼく"},{"t":"にくれないか。」"}]},{"k":"p","r":[{"t":"と、"},{"b":"今度","f":"こんど"},{"b":"力蔵","f":"りきぞう"},{"t":"は"},{"b":"良吉","f":"りょうきち"},{"t":"に"},{"b":"向","f":"む"},{"t":"かって"},{"b":"頼","f":"たの"},{"t":"みました。"},{"b":"良吉","f":"りょうきち"},{"t":"は"},{"b":"快","f":"こころよ"},{"t":"く"},{"b":"承諾","f":"しょうだく"},{"t":"して、その"},{"b":"笛","f":"ふえ"},{"t":"を"},{"b":"力蔵","f":"りきぞう"},{"t":"に"},{"b":"与","f":"あた"},{"t":"えました。そして、"},{"b":"自分","f":"じぶん"},{"t":"ははじめてオルゴールを"},{"b":"手","f":"て"},{"t":"に"},{"b":"持","f":"も"},{"t":"つことができて"},{"b":"大事","f":"だいじ"},{"t":"そうにして、この"},{"b":"不思議","f":"ふしぎ"},{"t":"な"},{"b":"音色","f":"ねいろ"},{"t":"のする"},{"b":"機械","f":"きかい"},{"t":"をながめていました。すると"},{"b":"力蔵","f":"りきぞう"},{"t":"はすこしばかりたつと"},{"b":"彼","f":"かれ"},{"t":"のそばにやってきて、"}]},{"k":"p","r":[{"t":"「"},{"b":"僕","f":"ぼく"},{"t":"はもう"},{"b":"家","f":"うち"},{"t":"へ"},{"b":"帰","f":"かえ"},{"t":"るんだから、オルゴールを"},{"b":"返","f":"かえ"},{"t":"しておくれ。」"}]},{"k":"p","r":[{"t":"といって、"},{"b":"良吉","f":"りょうきち"},{"t":"からそれを"},{"b":"取","f":"と"},{"t":"り"},{"b":"返","f":"かえ"},{"t":"して"},{"b":"持","f":"も"},{"t":"ってゆきました。その"},{"b":"後","f":"あと"},{"t":"で、"},{"b":"良吉","f":"りょうきち"},{"t":"はさも"},{"b":"名残惜","f":"なごりお"},{"t":"しそうにして、"},{"b":"力蔵","f":"りきぞう"},{"t":"の"},{"b":"後","f":"うし"},{"t":"ろ"},{"b":"姿","f":"すがた"},{"t":"を"},{"b":"見送","f":"みおく"},{"t":"っていました。"}]},{"k":"p","r":[{"t":"　"},{"b":"良吉","f":"りょうきち"},{"t":"の"},{"b":"住","f":"す"},{"t":"んでいる"},{"b":"家","f":"うち"},{"t":"はあばら"},{"b":"屋","f":"や"},{"t":"でありました。そして、"},{"b":"良吉","f":"りょうきち"},{"t":"は"},{"b":"床","f":"とこ"},{"t":"の"},{"b":"中","f":"なか"},{"t":"に"},{"b":"入","f":"はい"},{"t":"ってから、"},{"b":"昼間","f":"ひるま"},{"b":"見","f":"み"},{"t":"たオルゴールや、"},{"b":"飛行機","f":"ひこうき"},{"t":"のことなどが"},{"b":"心","f":"こころ"},{"t":"の"},{"b":"目","f":"め"},{"t":"からとれないで、それを"},{"b":"思","f":"おも"},{"t":"い"},{"b":"出","f":"だ"},{"t":"して"},{"b":"天","f":"てん"},{"t":"じょうを"},{"b":"仰","f":"あお"},{"t":"いでいますと、"},{"b":"窓","f":"まど"},{"t":"から、はるか"},{"b":"高","f":"たか"},{"t":"い"},{"b":"青空","f":"あおぞら"},{"t":"に"},{"b":"輝","f":"かがや"},{"t":"いている"},{"b":"星","f":"ほし"},{"t":"の"},{"b":"光","f":"ひかり"},{"t":"がもれてきて、ちょうど"},{"b":"良吉","f":"りょうきち"},{"t":"の"},{"b":"顔","f":"かお"},{"t":"の"},{"b":"上","f":"うえ"},{"t":"を"},{"b":"照","f":"て"},{"t":"らしているのでありました。"}]},{"k":"p","r":[{"t":"　その"},{"b":"星","f":"ほし"},{"t":"の"},{"b":"光","f":"ひかり"},{"t":"はなんともいえない"},{"b":"美","f":"うつく"},{"t":"しい"},{"b":"光","f":"ひかり"},{"t":"を"},{"b":"放","f":"はな"},{"t":"っていました。"},{"b":"金色","f":"きんいろ"},{"t":"のもあれば、"},{"b":"銀色","f":"ぎんいろ"},{"t":"のもある。また"},{"b":"緑色","f":"みどりいろ"},{"t":"のもあれば、"},{"b":"紫色","f":"むらさきいろ"},{"t":"のも、"},{"b":"青色","f":"あおいろ"},{"t":"のもありました。"},{"b":"良吉","f":"りょうきち"},{"t":"は、"},{"b":"自分","f":"じぶん"},{"t":"はなんのおもちゃも、また"},{"b":"珍","f":"めずら"},{"t":"しいものも"},{"b":"持","f":"も"},{"t":"たないけれど、この"},{"b":"空","f":"そら"},{"t":"の"},{"b":"星","f":"ほし"},{"t":"だけは"},{"b":"自分","f":"じぶん"},{"t":"のものにきめておこうと"},{"b":"思","f":"おも"},{"t":"いました。そして"},{"b":"毎晩","f":"まいばん"},{"t":"、あの"},{"b":"星","f":"ほし"},{"t":"の"},{"b":"光","f":"ひかり"},{"t":"をみつめて"},{"b":"寝","f":"ね"},{"t":"ようと"},{"b":"思","f":"おも"},{"t":"いました。"}]},{"k":"p","r":[{"t":"　"},{"b":"良吉","f":"りょうきち"},{"t":"は、"},{"b":"毎晩","f":"まいばん"},{"t":"、"},{"b":"寝床","f":"ねどこ"},{"t":"の"},{"b":"中","f":"なか"},{"t":"に"},{"b":"入","f":"はい"},{"t":"ると、"},{"b":"窓","f":"まど"},{"t":"からもれる"},{"b":"星","f":"ほし"},{"t":"の"},{"b":"光","f":"ひかり"},{"t":"を"},{"b":"見","f":"み"},{"t":"ていろいろのことを"},{"b":"考","f":"かんが"},{"t":"えていました。――すると、ある"},{"b":"晩","f":"ばん"},{"t":"のこと、"},{"b":"不思議","f":"ふしぎ"},{"t":"にも"},{"b":"窓","f":"まど"},{"t":"から、"},{"b":"彼","f":"かれ"},{"t":"を"},{"b":"手招","f":"てまね"},{"t":"ぐものがあります。"},{"b":"良吉","f":"りょうきち"},{"t":"は"},{"b":"起","f":"お"},{"t":"きていってみますと、それは"},{"b":"文雄","f":"ふみお"},{"t":"でありました。"},{"b":"良吉","f":"りょうきち"},{"t":"はあまりのなつかしさに"},{"b":"文雄","f":"ふみお"},{"t":"の"},{"b":"手","f":"て"},{"t":"を"},{"b":"堅","f":"かた"},{"t":"く"},{"b":"握","f":"にぎ"},{"t":"りしめました。"}]},{"k":"p","r":[{"t":"「"},{"b":"僕","f":"ぼく"},{"t":"はあの"},{"b":"星","f":"ほし"},{"t":"の"},{"b":"世界","f":"せかい"},{"t":"へいっているんだよ、"},{"b":"星","f":"ほし"},{"t":"の"},{"b":"世界","f":"せかい"},{"t":"にはもっと"},{"b":"速","f":"はや"},{"t":"い、いい"},{"b":"飛行機","f":"ひこうき"},{"t":"もあれば、もっといい"},{"b":"音色","f":"ねいろ"},{"t":"のする"},{"b":"楽器","f":"がっき"},{"t":"もあるよ。"},{"b":"今度","f":"こんど"},{"t":"くるときに"},{"b":"僕","f":"ぼく"},{"t":"は"},{"b":"持","f":"も"},{"t":"ってきて"},{"b":"君","f":"きみ"},{"t":"にあげるよ。"},{"b":"僕","f":"ぼく"},{"t":"は、いまその"},{"b":"飛行機","f":"ひこうき"},{"t":"に"},{"b":"乗","f":"の"},{"t":"ってきたのだ。これから"},{"b":"僕","f":"ぼく"},{"t":"は"},{"b":"毎晩","f":"まいばん"},{"t":"、ここへたずねてくるよ。だから"},{"b":"君","f":"きみ"},{"t":"はもうさびしがらなくていいよ。」"}]},{"k":"p","r":[{"t":"と、"},{"b":"文雄","f":"ふみお"},{"t":"はいいました。"}]},{"k":"p","r":[{"t":"「ああ、ほんとうに"},{"b":"君","f":"きみ"},{"t":"は"},{"b":"毎晩","f":"まいばん"},{"b":"遊","f":"あそ"},{"t":"びにきておくれよ。"},{"b":"僕","f":"ぼく"},{"t":"はさびしくてたまらないのだから。」"}]},{"k":"p","r":[{"t":"と、"},{"b":"良吉","f":"りょうきち"},{"t":"は"},{"b":"目","f":"め"},{"t":"から"},{"b":"熱","f":"あつ"},{"t":"い"},{"b":"涙","f":"なみだ"},{"t":"を"},{"b":"流","f":"なが"},{"t":"して、"},{"b":"友","f":"とも"},{"t":"の"},{"b":"手","f":"て"},{"t":"にすがりました。しかし"},{"b":"友","f":"とも"},{"t":"の"},{"b":"手","f":"て"},{"t":"は"},{"b":"氷","f":"こおり"},{"t":"のように"},{"b":"冷","f":"つめ"},{"t":"たかったのです。そして、"},{"b":"顔","f":"かお"},{"t":"の"},{"b":"色","f":"いろ"},{"t":"は、ろうのようにすきとおって"},{"b":"見","f":"み"},{"t":"えました。"},{"b":"良吉","f":"りょうきち"},{"t":"は"},{"b":"変","f":"か"},{"t":"わり"},{"b":"果","f":"は"},{"t":"てた"},{"b":"友","f":"とも"},{"t":"の"},{"b":"姿","f":"すがた"},{"t":"が"},{"b":"悲","f":"かな"},{"t":"しくて、また"},{"b":"泣","f":"な"},{"t":"いたのであります。"}]}]}