{"id":"051096","title":"島の暮れ方の話","author":"小川未明","authorId":"001475","blocks":[{"k":"p","r":[{"t":"　"},{"b":"南方","f":"なんぽう"},{"t":"の"},{"b":"暖","f":"あたた"},{"t":"かな"},{"b":"島","f":"しま"},{"t":"でありました。そこには"},{"b":"冬","f":"ふゆ"},{"t":"といっても、"},{"b":"名","f":"な"},{"t":"ばかりで、いつも"},{"b":"花","f":"はな"},{"t":"が"},{"b":"咲","f":"さ"},{"t":"き"},{"b":"乱","f":"みだ"},{"t":"れていました。"}]},{"k":"p","r":[{"t":"　ある"},{"b":"早春","f":"そうしゅん"},{"t":"の、"},{"b":"黄昏","f":"たそがれ"},{"t":"のことでありました。"},{"b":"一人","f":"ひとり"},{"t":"の"},{"b":"旅人","f":"たびびと"},{"t":"は、"},{"b":"道","f":"みち"},{"t":"を"},{"b":"急","f":"いそ"},{"t":"いでいました。このあたりは、はじめてとみえて、"},{"b":"右","f":"みぎ"},{"t":"を"},{"b":"見","f":"み"},{"t":"たり、"},{"b":"左","f":"ひだり"},{"t":"を"},{"b":"見","f":"み"},{"t":"たりして、"},{"b":"自分","f":"じぶん"},{"t":"のゆく"},{"b":"村","f":"むら"},{"t":"を"},{"b":"探","f":"さが"},{"t":"していたのであります。"}]},{"k":"p","r":[{"t":"　この"},{"b":"旅人","f":"たびびと"},{"t":"は、ここにくるまでには、"},{"b":"長","f":"なが"},{"t":"い"},{"b":"道","f":"みち"},{"t":"を"},{"b":"歩","f":"ある"},{"t":"きました。また、"},{"b":"船","f":"ふね"},{"t":"にも"},{"b":"乗","f":"の"},{"t":"らなければなりませんでした。"},{"b":"遠","f":"とお"},{"t":"い"},{"b":"国","f":"くに"},{"t":"から、この"},{"b":"島","f":"しま"},{"t":"に"},{"b":"住","f":"す"},{"t":"んでいる、"},{"b":"親戚","f":"しんせき"},{"t":"のものをたずねてきたのであります。"}]},{"k":"p","r":[{"t":"　"},{"b":"旅人","f":"たびびと"},{"t":"は、"},{"b":"道","f":"みち"},{"t":"ばたに"},{"b":"水仙","f":"すいせん"},{"t":"の"},{"b":"花","f":"はな"},{"t":"が"},{"b":"夢","f":"ゆめ"},{"t":"のように"},{"b":"咲","f":"さ"},{"t":"いているのを"},{"b":"見","f":"み"},{"t":"ました。また、"},{"b":"山","f":"やま"},{"t":"に"},{"b":"真","f":"ま"},{"t":"っ"},{"b":"赤","f":"か"},{"t":"なつばきの"},{"b":"花","f":"はな"},{"t":"が"},{"b":"咲","f":"さ"},{"t":"いているのを"},{"b":"見","f":"み"},{"t":"ました。そして、そのあたりは"},{"b":"野原","f":"のはら"},{"t":"や、"},{"b":"丘","f":"おか"},{"t":"であって、"},{"b":"人家","f":"じんか"},{"t":"というものを"},{"b":"見","f":"み"},{"t":"ませんでした。"},{"b":"暖","f":"あたた"},{"t":"かな"},{"b":"風","f":"かぜ"},{"t":"は、"},{"b":"海","f":"うみ"},{"t":"の"},{"b":"方","f":"ほう"},{"t":"から"},{"b":"吹","f":"ふ"},{"t":"いてきました。その"},{"b":"風","f":"かぜ"},{"t":"には、"},{"b":"花","f":"はな"},{"t":"の"},{"b":"香","f":"かお"},{"t":"りが"},{"b":"含","f":"ふく"},{"t":"んでいました。そして、"},{"b":"日","f":"ひ"},{"t":"はだんだんと"},{"b":"西","f":"にし"},{"t":"の"},{"b":"山","f":"やま"},{"t":"の"},{"b":"端","f":"は"},{"t":"に"},{"b":"沈","f":"しず"},{"t":"みかけていたのであります。"}]},{"k":"p","r":[{"t":"「もう"},{"b":"日","f":"ひ"},{"t":"が"},{"b":"暮","f":"く"},{"t":"れかかるが、どう"},{"b":"道","f":"みち"},{"t":"をいったら、"},{"b":"自分","f":"じぶん"},{"t":"のゆこうとする"},{"b":"村","f":"むら"},{"t":"に"},{"b":"着","f":"つ"},{"t":"くだろう。」と、"},{"b":"旅人","f":"たびびと"},{"t":"は"},{"b":"立","f":"た"},{"t":"ち"},{"b":"止","f":"ど"},{"t":"まって"},{"b":"思案","f":"しあん"},{"t":"しました。"}]},{"k":"p","r":[{"t":"　どうか、このあたりに、"},{"b":"聞","f":"き"},{"t":"くような"},{"b":"家","f":"うち"},{"t":"が、ないかと、また、しばらく、"},{"b":"右","f":"みぎ"},{"t":"を"},{"b":"見","f":"み"},{"t":"たり、"},{"b":"左","f":"ひだり"},{"t":"を"},{"b":"見","f":"み"},{"t":"たりして"},{"b":"歩","f":"ある"},{"t":"いてゆきました。ただ、"},{"b":"波","f":"なみ"},{"t":"の"},{"b":"岩","f":"いわ"},{"t":"に"},{"b":"打","f":"う"},{"t":"ち"},{"b":"寄","f":"よ"},{"t":"せて"},{"b":"砕","f":"くだ"},{"t":"ける"},{"b":"音","f":"おと"},{"t":"が、"},{"b":"静","f":"しず"},{"t":"かな"},{"b":"夕空","f":"ゆうぞら"},{"t":"の"},{"b":"下","f":"した"},{"t":"に、かすかに"},{"b":"聞","f":"き"},{"t":"こえてくるばかりであります。"}]},{"k":"p","r":[{"t":"　このとき、ふと"},{"b":"旅人","f":"たびびと"},{"t":"は、あちらに一"},{"b":"軒","f":"けん"},{"t":"のわら"},{"b":"屋","f":"や"},{"t":"を"},{"b":"見","f":"み"},{"t":"つけました。その"},{"b":"屋根","f":"やね"},{"t":"はとび"},{"b":"色","f":"いろ"},{"t":"がかっていました。"},{"b":"彼","f":"かれ"},{"t":"はその"},{"b":"家","f":"いえ"},{"t":"の"},{"b":"方","f":"ほう"},{"t":"に"},{"b":"近","f":"ちか"},{"t":"づいてゆきますと、みすぼらしい"},{"b":"家","f":"いえ"},{"t":"であって、"},{"b":"垣根","f":"かきね"},{"t":"などが"},{"b":"壊","f":"こわ"},{"t":"れて、"},{"b":"手","f":"て"},{"t":"を"},{"b":"入","f":"い"},{"t":"れたようすとてありません。"},{"b":"彼","f":"かれ"},{"t":"は、だれが、その"},{"b":"家","f":"いえ"},{"t":"に"},{"b":"住","f":"す"},{"t":"んでいるのだろうと"},{"b":"思","f":"おも"},{"t":"いました。"}]},{"k":"p","r":[{"t":"　だんだん"},{"b":"近","f":"ちか"},{"t":"づくと、"},{"b":"旅人","f":"たびびと"},{"t":"は、二"},{"b":"度","f":"ど"},{"t":"びっくりいたしました。それはそれは"},{"b":"美","f":"うつく"},{"t":"しい、いままでに"},{"b":"見","f":"み"},{"t":"たことのないような、"},{"b":"若","f":"わか"},{"t":"い"},{"b":"女","f":"おんな"},{"t":"がその"},{"b":"家","f":"いえ"},{"t":"の"},{"b":"門","f":"もん"},{"t":"にしょんぼりと"},{"b":"立","f":"た"},{"t":"っていたのでした。"}]},{"k":"p","r":[{"t":"　"},{"b":"女","f":"おんな"},{"t":"は、"},{"b":"長","f":"なが"},{"t":"い"},{"b":"髪","f":"かみ"},{"t":"を"},{"b":"肩","f":"かた"},{"t":"から"},{"b":"後","f":"うし"},{"t":"ろに"},{"b":"垂","f":"た"},{"t":"れていました。"},{"b":"歯","f":"は"},{"t":"は"},{"b":"細","f":"こま"},{"t":"かく"},{"b":"清","f":"きよ"},{"t":"らかで、"},{"b":"目","f":"め"},{"t":"は、すきとおるように"},{"b":"澄","f":"す"},{"t":"んでいて、"},{"b":"唇","f":"くちびる"},{"t":"は"},{"b":"花","f":"はな"},{"t":"のようにうるわしく、その"},{"b":"額","f":"ひたい"},{"t":"の"},{"b":"色","f":"いろ"},{"t":"は"},{"b":"白","f":"しろ"},{"t":"かったのです。"}]},{"k":"p","r":[{"t":"　"},{"b":"旅人","f":"たびびと"},{"t":"は、どうして、こんな"},{"b":"島","f":"しま"},{"t":"に、こうした"},{"b":"美","f":"うつく"},{"t":"しい"},{"b":"女","f":"おんな"},{"t":"が"},{"b":"住","f":"す"},{"t":"んでいるかと"},{"b":"思","f":"おも"},{"t":"いました。またこんな"},{"b":"島","f":"しま"},{"t":"だからこそ、こうした"},{"b":"美","f":"うつく"},{"t":"しい"},{"b":"女","f":"おんな"},{"t":"が"},{"b":"住","f":"す"},{"t":"んでいるのだとも"},{"b":"考","f":"かんが"},{"t":"えました。"}]},{"k":"p","r":[{"t":"　"},{"b":"旅人","f":"たびびと"},{"t":"は、"},{"b":"女","f":"おんな"},{"t":"の"},{"b":"前","f":"まえ"},{"t":"までいって、"}]},{"k":"p","r":[{"t":"「"},{"b":"私","f":"わたし"},{"t":"は、お"},{"b":"宮","f":"みや"},{"t":"のある"},{"b":"村","f":"むら"},{"t":"へゆきたいと"},{"b":"思","f":"おも"},{"t":"うのですが、どの"},{"b":"道","f":"みち"},{"t":"をいったらいいでしょうか。」といって、たずねました。"}]},{"k":"p","r":[{"t":"　"},{"b":"女","f":"おんな"},{"t":"は、にこやかに、さびしい"},{"b":"笑","f":"わら"},{"t":"いを"},{"b":"顔","f":"かお"},{"t":"にうかべました。"}]},{"k":"p","r":[{"t":"「あなたは、"},{"b":"旅","f":"たび"},{"t":"のお"},{"b":"人","f":"ひと"},{"t":"ですね。」といいました。"}]},{"k":"p","r":[{"t":"「そうです。」と、"},{"b":"旅人","f":"たびびと"},{"t":"は"},{"b":"答","f":"こた"},{"t":"えました。"}]},{"k":"p","r":[{"t":"　"},{"b":"女","f":"おんな"},{"t":"は、すこしばかり、ためらってみえましたが、"}]},{"k":"p","r":[{"t":"「わたしは、どうせあちらの"},{"b":"方","f":"ほう"},{"t":"までゆきますから、そこまで、ごいっしょにまいりましょう。」といいました。"}]},{"k":"p","r":[{"t":"　"},{"b":"旅人","f":"たびびと"},{"t":"は、「どうぞそうお"},{"b":"願","f":"ねが"},{"t":"いいたします。」と"},{"b":"頼","f":"たの"},{"t":"みました。そして、"},{"b":"二人","f":"ふたり"},{"t":"は、"},{"b":"道","f":"みち"},{"t":"を"},{"b":"歩","f":"ある"},{"t":"きかけたときに、"},{"b":"旅人","f":"たびびと"},{"t":"は、"},{"b":"女","f":"おんな"},{"t":"を"},{"b":"振","f":"ふ"},{"t":"り"},{"b":"向","f":"む"},{"t":"いて、"}]},{"k":"p","r":[{"t":"「あの"},{"b":"家","f":"いえ"},{"t":"は、あなたのお"},{"b":"住","f":"す"},{"t":"まいではないのですか？」とききました。すると、"},{"b":"女","f":"おんな"},{"t":"はやさしい"},{"b":"声","f":"こえ"},{"t":"で、"}]},{"k":"p","r":[{"t":"「いいえ、なんであれがわたしの"},{"b":"家","f":"うち"},{"t":"なものですか。"},{"b":"今日","f":"きょう"},{"t":"はわたしの"},{"b":"二人","f":"ふたり"},{"t":"の"},{"b":"子供","f":"こども"},{"t":"たちが、"},{"b":"遊","f":"あそ"},{"t":"びに"},{"b":"出","f":"で"},{"t":"て、まだ"},{"b":"帰","f":"かえ"},{"t":"ってきませんから、"},{"b":"迎","f":"むか"},{"t":"えに"},{"b":"出","f":"で"},{"t":"たのです。すると、あの"},{"b":"家","f":"いえ"},{"t":"の"},{"b":"壁板","f":"しとみ"},{"t":"に、"},{"b":"去年","f":"きょねん"},{"t":"いなくなった、わたしの"},{"b":"妹","f":"いもうと"},{"t":"の"},{"b":"着物","f":"きもの"},{"t":"に"},{"b":"似","f":"に"},{"t":"たのがかかっていましたので、ついぼんやりと"},{"b":"思案","f":"しあん"},{"t":"に"},{"b":"暮","f":"く"},{"t":"れていたのでございます。」と、"},{"b":"女","f":"おんな"},{"t":"は"},{"b":"答","f":"こた"},{"t":"えました。"}]},{"k":"p","r":[{"t":"　"},{"b":"旅人","f":"たびびと"},{"t":"は、"},{"b":"不思議","f":"ふしぎ"},{"t":"なことを"},{"b":"聞","f":"き"},{"t":"くものだと"},{"b":"驚","f":"おどろ"},{"t":"いて、"},{"b":"美","f":"うつく"},{"t":"しい"},{"b":"女","f":"おんな"},{"t":"の"},{"b":"横顔","f":"よこがお"},{"t":"をしみじみと"},{"b":"見守","f":"みまも"},{"t":"りました。ちょうど、そのとき、あちらから、"}]},{"k":"p","r":[{"t":"「お"},{"b":"母","f":"かあ"},{"t":"さん！」"}]},{"k":"p","r":[{"t":"「お"},{"b":"母","f":"かあ"},{"t":"さん！」"}]},{"k":"p","r":[{"t":"といって、"},{"b":"二人","f":"ふたり"},{"t":"のかわいらしい"},{"b":"子供","f":"こども"},{"t":"が"},{"b":"駆","f":"か"},{"t":"けてきました。"},{"b":"女","f":"おんな"},{"t":"は、"},{"b":"喜","f":"よろこ"},{"t":"んで、"},{"b":"二人","f":"ふたり"},{"t":"の"},{"b":"子供","f":"こども"},{"t":"を"},{"b":"自分","f":"じぶん"},{"t":"の"},{"b":"胸","f":"むね"},{"t":"に"},{"b":"抱","f":"だ"},{"t":"きました。"}]},{"k":"p","r":[{"t":"「わたしたちは、ここでお"},{"b":"別","f":"わか"},{"t":"れいたします。あなたは、この"},{"b":"道","f":"みち"},{"t":"をまっすぐにおゆきなさると、じきにお"},{"b":"宮","f":"みや"},{"t":"のある"},{"b":"村","f":"むら"},{"t":"に"},{"b":"出","f":"で"},{"t":"ますから。」と、"},{"b":"女","f":"おんな"},{"t":"は"},{"b":"旅人","f":"たびびと"},{"t":"に"},{"b":"道","f":"みち"},{"t":"を"},{"b":"教","f":"おし"},{"t":"えて、"},{"b":"花","f":"はな"},{"t":"の"},{"b":"咲","f":"さ"},{"t":"く、"},{"b":"細道","f":"ほそみち"},{"t":"を"},{"b":"二人","f":"ふたり"},{"t":"の"},{"b":"女","f":"おんな"},{"t":"の"},{"b":"子","f":"こ"},{"t":"といっしょに、さびしい、"},{"b":"波","f":"なみ"},{"t":"の"},{"b":"音","f":"おと"},{"t":"の"},{"b":"聞","f":"き"},{"t":"こえる"},{"b":"山","f":"やま"},{"t":"のすその"},{"b":"方","f":"ほう"},{"t":"へと"},{"b":"指","f":"さ"},{"t":"してゆきました。"}]},{"k":"p","r":[{"t":"　"},{"b":"旅人","f":"たびびと"},{"t":"は、それと"},{"b":"反対","f":"はんたい"},{"t":"に"},{"b":"山","f":"やま"},{"t":"について、だんだん"},{"b":"奥","f":"おく"},{"t":"に"},{"b":"深","f":"ふか"},{"t":"く"},{"b":"入","f":"はい"},{"t":"ってゆきました。"},{"b":"山々","f":"やまやま"},{"t":"にはみかんが、まだなっているところもありました。そして、まったく、"},{"b":"日","f":"ひ"},{"t":"が"},{"b":"暮","f":"く"},{"t":"れた"},{"b":"時分","f":"じぶん"},{"t":"、"},{"b":"思","f":"おも"},{"t":"った"},{"b":"村","f":"むら"},{"t":"につくことができたのであります。"}]},{"k":"p","r":[{"t":"　その"},{"b":"夜","f":"よ"},{"t":"、"},{"b":"燈火","f":"ともしび"},{"t":"の"},{"b":"下","f":"した"},{"t":"で"},{"b":"旅人","f":"たびびと"},{"t":"は、"},{"b":"親戚","f":"しんせき"},{"t":"の"},{"b":"人々","f":"ひとびと"},{"t":"に、その"},{"b":"日","f":"ひ"},{"b":"不思議","f":"ふしぎ"},{"t":"な"},{"b":"美","f":"うつく"},{"t":"しい"},{"b":"女","f":"おんな"},{"t":"を"},{"b":"見","f":"み"},{"t":"たこと、そして、その"},{"b":"女","f":"おんな"},{"t":"はあちらのさびしい、"},{"b":"山","f":"やま"},{"t":"のすその"},{"b":"方","f":"ほう"},{"t":"へと"},{"b":"草道","f":"くさみち"},{"t":"を"},{"b":"分","f":"わ"},{"t":"けていったことを、"},{"b":"話","f":"はな"},{"t":"したのであります。"}]},{"k":"p","r":[{"t":"　そのとき、"},{"b":"親戚","f":"しんせき"},{"t":"の"},{"b":"人","f":"ひと"},{"t":"は、"},{"b":"驚","f":"おどろ"},{"t":"いた"},{"b":"顔","f":"かお"},{"t":"つきをして、"}]},{"k":"p","r":[{"t":"「あんな"},{"b":"方","f":"ほう"},{"t":"には、"},{"b":"家","f":"いえ"},{"t":"がないはずだが。」といいました。"}]},{"k":"p","r":[{"t":"　"},{"b":"旅人","f":"たびびと"},{"t":"は、また、「"},{"b":"妹","f":"いもうと"},{"t":"の"},{"b":"着物","f":"きもの"},{"t":"に、よく"},{"b":"似","f":"に"},{"t":"た"},{"b":"着物","f":"きもの"},{"t":"が"},{"b":"壁板","f":"しとみ"},{"t":"にかかっていた――その"},{"b":"妹","f":"いもうと"},{"t":"は、"},{"b":"去年","f":"きょねん"},{"b":"行方","f":"ゆくえ"},{"t":"がわからなくなった――。」といった"},{"b":"女","f":"おんな"},{"t":"の"},{"b":"言葉","f":"ことば"},{"t":"を、いぶかしく"},{"b":"思","f":"おも"},{"t":"わずにはいられませんでした。"}]},{"k":"p","r":[{"t":"　"},{"b":"翌日","f":"よくじつ"},{"t":"、"},{"b":"旅人","f":"たびびと"},{"t":"は、"},{"b":"親戚","f":"しんせき"},{"t":"の"},{"b":"人","f":"ひと"},{"t":"といっしょに、"},{"b":"昨日","f":"きのう"},{"t":"、"},{"b":"女","f":"おんな"},{"t":"がその"},{"b":"家","f":"いえ"},{"t":"の"},{"b":"門","f":"かど"},{"t":"に"},{"b":"立","f":"た"},{"t":"っていたところまでいってみることにしました。"}]},{"k":"p","r":[{"t":"　"},{"b":"南","f":"みなみ"},{"t":"の"},{"b":"島","f":"しま"},{"t":"の"},{"b":"気候","f":"きこう"},{"t":"は、"},{"b":"暖","f":"あたた"},{"t":"かで"},{"b":"空","f":"そら"},{"t":"はうっとりしていました。そして、みつばちは、"},{"b":"花","f":"はな"},{"t":"に"},{"b":"集","f":"あつ"},{"t":"まっていました。"},{"b":"旅人","f":"たびびと"},{"t":"は、"},{"b":"昨日","f":"きのう"},{"t":"の"},{"b":"黄昏方","f":"たそがれがた"},{"b":"見","f":"み"},{"t":"たわら"},{"b":"屋","f":"や"},{"t":"までやってきますと、その"},{"b":"家","f":"うち"},{"t":"は、まったくの"},{"b":"破","f":"やぶ"},{"t":"れ"},{"b":"家","f":"や"},{"t":"で、だれも"},{"b":"住","f":"す"},{"t":"んでいませんでした。そして、"},{"b":"壁板","f":"しとみ"},{"t":"のところをながめますと、"},{"b":"美","f":"うつく"},{"t":"しいちょうの"},{"b":"翼","f":"つばさ"},{"t":"が、"},{"b":"大","f":"おお"},{"t":"きなくもの"},{"b":"巣","f":"す"},{"t":"にかかっていたのでありました。"}]}]}