{"id":"057479","title":"閑山","author":"坂口安吾","authorId":"001095","blocks":[{"k":"p","r":[{"t":"　昔、越後之国魚沼の"},{"b":"僻地","f":"へきち"},{"t":"に、閑山寺の六袋和尚といって近隣に徳望高い老僧があった。"}]},{"k":"p","r":[{"t":"　初冬の"},{"b":"深更","f":"しんこう"},{"t":"のこと、雪明りを愛ずるまま"},{"b":"写経","f":"しゃきょう"},{"t":"に時を忘れていると、窓外から毛の生えた手を差しのべて顔をなでるものがあった。"},{"b":"和尚","f":"おしょう"},{"t":"は朱筆に持ちかえて、その掌に花の字を書きつけ、あとは"},{"b":"余念","f":"よねん"},{"t":"もなく再び写経に"},{"b":"没頭","f":"ぼっとう"},{"t":"した。"}]},{"k":"p","r":[{"t":"　明方ちかく、窓外から、"},{"b":"頻","f":"しき"},{"t":"りに泣き叫ぶ声が起った。やがて先ほどの手を再び差しのべる者があり、声が言うには「和尚さま。誤って有徳の"},{"b":"沙門","f":"しゃもん"},{"t":"を"},{"b":"嬲","f":"なぶ"},{"t":"り、お書きなさいました文字の重さに、帰る道が歩けませぬ。"},{"b":"不愍","f":"ふびん"},{"t":"と思い、文字を落して下さりませ」見れば一匹の狸であった。"},{"b":"硯","f":"すずり"},{"t":"の水を筆にしめして、掌の文字を洗ってやると、雪上の蔭間を"},{"b":"縫","f":"ぬ"},{"t":"い、闇の奥へ消え去った。"}]},{"k":"p","r":[{"t":"　翌晩、坊舎の窓を叩き、"},{"b":"訪","f":"おとな"},{"t":"う声がした。雨戸を開けると、昨夜の狸が手に"},{"b":"栂","f":"つが"},{"t":"の小枝をたずさえ、それを室内へ投げ入れて、逃げ去った。"}]},{"k":"p","r":[{"t":"　その後、夜毎に、季節の木草をたずさえて、窓を訪れる習いとなった。追々"},{"b":"昵懇","f":"じっこん"},{"t":"を重ねて心置きなく物を言う間柄となるうちに、独居の和尚の不便を案じて、なにくれと小用に立働くようになり、いつとなくその高風に感じ入って自ら小坊主に姿を変え、側近に仕えることとなった。"}]},{"k":"p","r":[{"t":"　この狸は通称を団九郎と言い、"},{"b":"眷属","f":"けんぞく"},{"t":"では名の知れた一匹であったそうな。ほどなく経文を"},{"b":"暗","f":"そら"},{"t":"んじて"},{"b":"諷経","f":"ふうきょう"},{"t":"に唱和し、また作法を覚えて朝夜の"},{"b":"坐禅","f":"ざぜん"},{"t":"に加わり、"},{"b":"敢","f":"あえ"},{"t":"て三十棒を怖れなかった。"}]},{"k":"p","r":[{"t":"　六袋和尚は和歌俳諧をよくし、又、折にふれて仏像、菩薩像、羅漢像等を刻んだ。その羅漢像、居士像等には"},{"b":"狗狸","f":"くり"},{"t":"に類似の面相もあったというが、恐らく偶然の所産であって、団九郎に関係はなかったのだろう。"}]},{"k":"p","r":[{"t":"　いつとなく、団九郎も"},{"b":"彫像","f":"ちょうぞう"},{"t":"の"},{"b":"三昧","f":"さんまい"},{"t":"を知った。木材をさがしもとめ、和尚の"},{"b":"熟睡","f":"じゅくすい"},{"t":"をまって庫裏の一隅に"},{"b":"胡座","f":"あぐら"},{"t":"し、"},{"b":"鑿","f":"のみ"},{"t":"を"},{"b":"揮","f":"ふる"},{"t":"いはじめてのちには、雑念を離れ、屡"},{"g":"〓","d":"二の字点、1-2-22"},{"b":"","f":"しばしば"},{"t":"夜の白むのも忘れていたということである。"}]},{"k":"p","r":[{"t":"　六袋和尚は六日先んじて"},{"b":"己","f":"おの"},{"t":"れの死期を予知した。諸般のことを"},{"b":"調","f":"ととの"},{"t":"え、"},{"b":"辞世","f":"じせい"},{"t":"の句もなく、特別の言葉もなく、"},{"b":"恰","f":"あたか"},{"t":"も前栽へ逍遥に立つ人のように"},{"b":"入寂","f":"にゅうじゃく"},{"t":"した。"}]},{"k":"blank"},{"k":"p","r":[{"t":"　参禅の三摩地を味い、諷経"},{"b":"念誦","f":"ねんじゅ"},{"t":"の"},{"b":"法悦","f":"ほうえつ"},{"t":"を知っていたので、和尚の"},{"b":"遷化","f":"せんげ"},{"t":"して後も、団九郎は閑山寺を去らなかった。"},{"b":"五蘊","f":"ごうん"},{"t":"の"},{"b":"覊絆","f":"きはん"},{"t":"を厭悪し、すでに一念"},{"b":"解脱","f":"げだつ"},{"t":"を"},{"b":"発心","f":"ほっしん"},{"t":"していたのである。"}]},{"k":"p","r":[{"t":"　新らたな住持は弁兆と言った。彼は単純な酒徒であった。先住の高風に比べれば百難あったが、彼も亦一生不犯の"},{"b":"戒律","f":"かいりつ"},{"t":"を守り、"},{"b":"専","f":"もっぱ"},{"t":"ら一酔また一睡に一日の悦びを"},{"b":"托","f":"たく"},{"t":"していた無難な坊主のひとりであった。"}]},{"k":"p","r":[{"t":"　弁兆は食膳の"},{"b":"吟味","f":"ぎんみ"},{"t":"に心をくばり、"},{"b":"一汁","f":"いちじゅう"},{"t":"の風味にもあれこれと工夫を命じた。団九郎の坐禅諷経を"},{"b":"封","f":"ふう"},{"t":"じて、山陰へ木の芽をとらせに走らせ、又、屡"},{"g":"〓","d":"二の字点、1-2-22"},{"b":"","f":"しばしば"},{"b":"蕎麦","f":"そば"},{"t":"を打たせた。一酔をもとめてのちは、肩をもませて、やがて"},{"b":"大蘿蔔頭","f":"だいらふとう"},{"t":"（だいこん）の煮ゆるが如く眠りに落ちた。ことごとく、団九郎の意外であった。一言一動俗臭"},{"b":"芬々","f":"ふんぷん"},{"t":"として、"},{"b":"甚","f":"はなは"},{"t":"だ正視に堪えなかった。"}]},{"k":"p","r":[{"t":"　一夕、"},{"b":"雲水","f":"うんすい"},{"t":"の僧に変じて、団九郎は山門をくぐった。折から弁兆は小坊主の無断不在をかこちながら、酒食の支度に余念もなかった。"}]},{"k":"p","r":[{"t":"　雲水の僧は身の丈六尺有余、"},{"b":"筋骨","f":"きんこつ"},{"t":"隆々として、手足は古木のようであった。両眼は"},{"b":"炬火","f":"きょか"},{"t":"の如くに燃え、両頬は岩塊の如く、"},{"b":"鼻孔","f":"びこう"},{"t":"は風を吹き、口は荒縄を"},{"b":"縒","f":"よ"},{"t":"り合せたようであった。"}]},{"k":"p","r":[{"t":"　雲水の僧は"},{"b":"庫裏","f":"くり"},{"t":"へ現れ、弁兆の眼前を立ちふさいだ。それから、破れ鐘のような"},{"b":"大音声","f":"だいおんじょう"},{"t":"でこう問うた。"}]},{"k":"p","r":[{"t":"「噇酒糟の漢（のんだくれめ）仏法を喰うや如何に」"}]},{"k":"p","r":[{"t":"　弁兆は徳利を落し、さて、"},{"b":"臍下丹田","f":"せいかたんでん"},{"t":"に力を籠めて、まず"},{"b":"大喝","f":"だいかつ"},{"t":"一番これに応じた。"}]},{"k":"p","r":[{"t":"　と、雲水の僧は、やおらかたえの"},{"b":"囲炉裏","f":"いろり"},{"t":"の上へ半身をかがめた。左手に右の衣袖を収めて、"},{"b":"紅蓮","f":"ぐれん"},{"t":"をふく火中深くその逞しい片腕を差し入れた。そうして、大いなる"},{"b":"燠","f":"おき"},{"t":"のひとつを"},{"b":"鷲掴","f":"わしづか"},{"t":"みにして、再び弁兆の眼前を立ちふさいだ。"}]},{"k":"p","r":[{"t":"「噇酒糟の漢よく仏法を喰うや如何に」"}]},{"k":"p","r":[{"t":"　雲水の僧はにじり寄って、真赤な燠を弁兆の鼻先へ突きつけた。弁兆に二喝を発する勇気がなかった。思わず色を失って、飛び退いていた。"}]},{"k":"p","r":[{"t":"「這の掠虚頭の漢（いんちきやろうめ）！」"}]},{"k":"p","r":[{"t":"　雲水の僧は"},{"b":"矢庭","f":"やにわ"},{"t":"に躍りかかって、弁兆の口中へ燠を"},{"b":"捩","f":"ね"},{"t":"じ込むところであった。弁兆は飛鳥の如くに身をひるがえして逃げていた。そのまま"},{"b":"逐電","f":"ちくでん"},{"t":"して、再び"},{"b":"行方","f":"ゆくえ"},{"t":"は知れなかった。"}]},{"k":"blank"},{"k":"p","r":[{"t":"　雲水の僧は住持となった。人"},{"b":"称","f":"よ"},{"t":"んで呑火和尚と言った。即ち団九郎狸であった。"},{"b":"懈怠","f":"けたい"},{"t":"を憎み、ひたすら見性成仏を念じて坐禅三昧に浸り、時に夜もすがら仏像を刻んで静寂な孤独を満喫した。"}]},{"k":"p","r":[{"t":"　村に久次というしれものがあった。大青道心の坐禅三昧を可笑しがり、法話の"},{"b":"集","f":"つど"},{"t":"いのある夕辺、庫裏へ忍び、和尚の食餌へやたらと砥粉をふりまいておいた。砥粉をくらえば止めようと欲してもおのずと"},{"b":"放屁","f":"ほうひ"},{"t":"して止める術がないという俗説があるのだそうな。"}]},{"k":"p","r":[{"t":"　果して和尚は、開口一番、放屁の誘惑に狼狽した。臍下丹田に力を"},{"b":"籠","f":"こ"},{"t":"めれば、放屁の音量を大にするばかりであり、丹田の力をぬけば、心気"},{"b":"顛倒","f":"てんとう"},{"t":"して為すところを失うばかりであった。"}]},{"k":"p","r":[{"t":"「しばらく誦経致そう」"}]},{"k":"p","r":[{"t":"　和尚は腹痛を押えてやおら立上り、木魚の前に端坐した。優婆塞優婆夷の合唱にかくれて、ひそかに始末する"},{"b":"魂胆","f":"こんたん"},{"t":"であった。そこで先ず試みに一微風を"},{"b":"漏脱","f":"ろうだつ"},{"t":"したところ、ことごとく思量に反して、あとはもはや大流風の思うがままの"},{"b":"奔出","f":"ほんしゅつ"},{"t":"を防ぎかける"},{"b":"手段","f":"てだて"},{"t":"もなかった。大風笛は高天井に木魂して、人々がこれを怪しみ誦経の声を呑んだ時には、転出する凸凹様々な風声のみが大小高低の妙を描きだすばかりであった。臭気堂に満ちて、人々は思わず"},{"b":"鼻孔","f":"びこう"},{"t":"に袖を当て、ひとりの立上る気配を知ると、我先きに堂を逃れた。"}]},{"k":"p","r":[{"t":"　釈迦牟尼成道の時にも"},{"b":"降魔","f":"こうま"},{"t":"のことがあった。正法には必ず"},{"b":"障礙","f":"しょうげ"},{"t":"のあるもの、放屁を抑えようとして四苦八苦するのも未だ法を"},{"b":"会得","f":"えとく"},{"t":"すること遠きがゆえであり、放屁の漏出に狼狽して為すところを忘れるのも未だ全機"},{"b":"透脱","f":"とうだつ"},{"t":"して大自在を得る底の"},{"b":"妙覚","f":"みょうかく"},{"t":"に到らざるがゆえである。即ち透脱して大自在を得たならば、"},{"b":"拈花","f":"ねんげ"},{"t":"も放屁も同一のものであるに相違ない。静夜端坐して、団九郎はかく観じた。"}]},{"k":"p","r":[{"t":"　それにつけても、俗人の"},{"b":"済度","f":"さいど"},{"t":"しがたいことを嘆いて、人里から一里ばかり山奥に庵を結び、遁世して禅定三昧に没入した。"}]},{"k":"blank"},{"k":"p","r":[{"t":"　冬がきて、田舎役者の一行がこの"},{"b":"草庵","f":"そうあん"},{"t":"を通りかかった。"}]},{"k":"p","r":[{"t":"　雪国の農夫達は冬毎にその故里の"},{"b":"生業","f":"せいぎょう"},{"t":"を失い、雪解けの頃まで他郷へ稼ぎにでかけるのが昔からの習いであった。部落によって、あるいは灘伊丹の酒男、あるいは江戸の奉公と様々であるが、所によっては、越後獅子の部落もあり、村廻りの神楽狂言芝居等を伝承するところもあった。もとより正業は農であるが、副業も亦"},{"b":"概","f":"おおむ"},{"t":"ね"},{"b":"世襲","f":"せしゅう"},{"t":"で、現今も尚このあたりには冬毎に芝居を巡業する部落がある。丈余の雪上に舞台を設え、観客も亦雪原に"},{"b":"筵","f":"むしろ"},{"t":"をしき、持参の重箱をひらいて酒をのみながら見物する。木戸として特に規定の金額がないから、金銭を支払う者は甚だ稀で、通例米味噌野菜酒等を木戸銭に代え、一族ひきつれて観覧にあつまる。演者はただひたすらに芝居を楽しむという風で、寒気厳烈の雪原とはいえさながらに"},{"b":"春風駘蕩","f":"しゅんぷうたいとう"},{"t":"、「三年さきに勘平の男前の若い衆はどうなすったね。女の子が夢中になったものだったが、達者かね」「あの野郎は"},{"b":"嬶","f":"かかあ"},{"t":"をもらって、今年は休ましてもらいますだとの」などいう会話が幕の間に舞台の上下で交わされる。座長と見える老爺など終生"},{"b":"水呑百姓","f":"みずのみびゃくしょう"},{"t":"の見るからに武骨そのものの"},{"b":"骨柄","f":"こつがら"},{"t":"であるが、巧みに女形をしこなして優美哀切を極め、涙の袖をしぼらせること、いつの年も変りがないということである。"}]},{"k":"p","r":[{"t":"　折から一行のひとりに病人ができた。通りかかった草庵をこれ幸いに無心して病人を"},{"b":"担","f":"かつ"},{"t":"ぎ入れたが、翌日も、また翌日も、はかばかしくいかない。先を急ぐ旅のこととて、ひとりの附添いを置き残して一座の者は立去った。"}]},{"k":"p","r":[{"t":"　病人は暮方から熱が高まり、夜は悪夢にうなされて"},{"b":"譫言","f":"たわごと"},{"t":"を言い、屡"},{"g":"〓","d":"二の字点、1-2-22"},{"b":"","f":"しばしば"},{"t":"水をもとめた。明方に漸く寝しずまるのが例であった。附添の男は和尚に"},{"b":"祈祷","f":"きとう"},{"t":"を"},{"b":"懇願","f":"こんがん"},{"t":"した。同村の某が同じような高熱に悩んだとき、真言の僧に祈祷を受け、"},{"b":"唵摩耶底連","f":"おんまやてれん"},{"t":"の札を水にうつしていただいたところ、翌日は熱も落ちて"},{"b":"本復","f":"ほんぷく"},{"t":"したことを思いだしたのであった。"}]},{"k":"p","r":[{"t":"「拙僧は"},{"b":"左様","f":"さよう"},{"t":"な法力を"},{"b":"会得","f":"えとく"},{"t":"した生きぼとけでは"},{"b":"厶","f":"ござ"},{"t":"らぬ」と和尚は答えた。「見られる通り俗世間を遁れ、一念解脱を発起した鈍根の青道心で厶る。死生を"},{"b":"大悟","f":"たいご"},{"t":"し、即心即仏非心非仏に到らんことを欲しながら、妄想尽きず、見透するところ甚だ浅薄な、"},{"b":"一尿床","f":"いちにょうしょう"},{"t":"の鬼子（寝小便たれ小僧）とは即ちこの坊主がこと。"},{"b":"加持","f":"かじ"},{"t":"祈祷は思いもより申さぬ」と受けつける気配もなかった。"}]},{"k":"p","r":[{"t":"　病人は日毎に衰え、すでに"},{"b":"起居","f":"ききょ"},{"t":"も不自由であった。"},{"b":"頻","f":"しき"},{"t":"りに故里の土を恋しがり、また人々をなつかしんだ。その音声も日を経るごとに力なく、附添いの友の嘆きを深くさせるのみだった。彼は執拗に和尚の祈祷を懇願した。"}]},{"k":"p","r":[{"t":"「定命はこれ定命で厶る。一切空と観じ、雑念あっては、"},{"b":"成仏","f":"じょうぶつ"},{"t":"なり申さぬぞ」"}]},{"k":"p","r":[{"t":"　和尚の答えは、いつもながら、それだけだった。傍に瀕死の病人もなきが如く、ひねもす"},{"b":"禅定三昧","f":"ぜんじょうざんまい"},{"t":"であった。その大いなる趺坐僧の姿は、"},{"b":"山寨","f":"さんさい"},{"t":"を構えて妖術を使う"},{"b":"蝦蟇","f":"がま"},{"t":"のように物々しく取澄して、とりつく島もない思いをさせた。"}]},{"k":"p","r":[{"t":"　さりとて病状は一途に悪化を"},{"b":"辿","f":"たど"},{"t":"るばかりで、人力の"},{"b":"施","f":"ほどこ"},{"t":"す術も見えないので、附添いの男は、暇あるたびに、坐禅三昧の和尚の膝をゆさぶって、法力の試みを"},{"b":"懇請","f":"こんせい"},{"t":"するほかに智慧の浮かぶゆとりはなかった。ゆさぶる膝の手応えは太根を張った大松の木の"},{"b":"瘤","f":"こぶ"},{"t":"かと思われるばかり、なかなか微動を揺りだすことも絶望に見える有様であった。"}]},{"k":"p","r":[{"t":"「生者は必滅のならい。執着して、"},{"b":"徒","f":"いたず"},{"t":"らに往生の"},{"b":"素懐","f":"そかい"},{"t":"を乱さるるな」"}]},{"k":"p","r":[{"t":"　和尚は俗人の執念を厭悪するものの如く、ときに不興をあらわして、言った。そうして、膝をゆさぶられても、半眼をひらこうとすらしなかった。"}]},{"k":"p","r":[{"t":"　然し、和尚の顔色も、病者の悪化に"},{"b":"競","f":"きそ"},{"t":"い立って、日に日に"},{"b":"光沢","f":"こうたく"},{"t":"を失い、その"},{"b":"逞","f":"たくま"},{"t":"しげな全身に、なんとなく衰えの気が漂った。"}]},{"k":"p","r":[{"t":"　春がきて、巡業の一行が再び草庵へ戻ったとき、すでに病人は臨終を待つばかりであった。人々は不幸な友の"},{"b":"枕頭","f":"ちんとう"},{"t":"に"},{"b":"凝坐","f":"ぎょうざ"},{"t":"して、悲嘆にくれたが、もとより人の思いによって消える命が取戻せようものではなかった。"}]},{"k":"p","r":[{"t":"　草庵の裏山に眺望ひらけた中腹の平地を探しもとめて、涙ながらに友のなきがらを"},{"b":"葬","f":"ほうむ"},{"t":"った。"},{"b":"回向","f":"えこう"},{"t":"、"},{"b":"引導","f":"いんどう"},{"t":"も型の如くに"},{"b":"執","f":"と"},{"t":"り行ったが、和尚の顔色は益"},{"g":"〓","d":"二の字点、1-2-22"},{"b":"","f":"ますます"},{"b":"勝","f":"すぐ"},{"t":"れず、"},{"b":"土気色","f":"つちけいろ"},{"t":"のむくみを表わし、"},{"b":"眉間","f":"みけん"},{"t":"の憂悶は隠しもあえず、全身衰微の色深く、歩く足にも力失せがちな有様がただならなかった。"}]},{"k":"p","r":[{"t":"　一座の長が進みでて、一様ならぬ長逗留の不始末を詫び、回向の労を深謝したとき、和尚が言った。"}]},{"k":"p","r":[{"t":"「されば、善根、回向は"},{"b":"比丘","f":"びく"},{"t":"のつとめ。ましてこの身は見られる如く世を捨てた沙門、お礼のことはひらに要り申さぬ。ただ、お言葉ゆえ、"},{"b":"所望","f":"しょもう"},{"t":"いたしてよろしいものなら、なにとぞ、一念発起の心根をあわれみ、"},{"b":"塵労","f":"じんろう"},{"t":"断ちがたい鈍根の青道心に"},{"b":"劬","f":"いた"},{"t":"わりを寄せ給いて、浮世の風が解脱の障礙とならぬよう、なるべく早う拙僧ひとりにさせて下されたい」"}]},{"k":"p","r":[{"t":"　語る言葉にも力なく息苦しげであった。"}]},{"k":"p","r":[{"t":"　人々は"},{"b":"俄","f":"にわ"},{"t":"かに興ざめ、遺品などとりまとめるにも心せかせて、いとまを告げたが、それを待つ間ももどかしげな和尚の様子に、ほとほと厭気さすばかりであった。"}]},{"k":"p","r":[{"t":"　人々がものの三四十間も歩いたころ、うしろに奇異な大音響が湧き起った。低く全山の地肌を這いわたる幅のひろいその音響を耳にしたとき、すでに人々の踏む足は自ら七八寸あまり宙に浮き、丹田に力の限り籠めてみても、音の自然に消え絶えるまで、再び土を踏むことができなかった。"}]},{"k":"p","r":[{"t":"　驚いて、草庵の方を振返ると、和尚は柱に"},{"b":"縋","f":"すが"},{"t":"りつき、呼吸は荒々しくその肩をふるわせていた。"}]},{"k":"p","r":[{"t":"　再び大音響を耳にしたとき、和尚の法衣は天に向って駈け去るが如く、裾は高々と空間に張りひろがり、人々の足は自然に踏む土を失って、再び宙に浮いていた。"}]},{"k":"blank"},{"k":"p","r":[{"b":"庵寺","f":"あんでら"},{"t":"の屁っこき坊主はの"}]},{"k":"p","r":[{"t":"山の粉雪も黄色にそめ"}]},{"k":"p","r":[{"t":"春のさかりに紅葉もさかせ"}]},{"k":"p","r":[{"t":"おないぶつに"},{"b":"尻","f":"けつ"},{"t":"向けて"},{"b":"罰","f":"ばち"},{"t":"当りとは面妖な"}]},{"k":"p","r":[{"t":"仏様も金びかりなら"}]},{"k":"p","r":[{"t":"　　　目出度い　目出度い"}]},{"k":"blank"},{"k":"p","r":[{"t":"　あるとき、和尚に依頼の筋があって、草庵を訪ねた村人があった。"}]},{"k":"p","r":[{"t":"　訪うまでもなく、坐禅三昧の和尚の姿が、まる見えであった。"}]},{"k":"p","r":[{"t":"「お頼み申します」"}]},{"k":"p","r":[{"t":"　と、訪客は和尚の後姿に向って、慎しみ深く訪いを通じた。"},{"b":"趺坐","f":"ふざ"},{"t":"の和尚に微動もなく、返事もなかった。四たび、五たび、訪客は次第に声を高らかにして、同じ訪いを繰返したが、さながら木像に物言う如く、さらに"},{"b":"手応","f":"てごた"},{"t":"えの気配がなかった。"}]},{"k":"p","r":[{"t":"　さて、所在もなさに見廻せば、すでに屋根は傾いて、所々に隙間をつくり、また大空ののぞけて見える"},{"b":"孔","f":"あな"},{"t":"もあった。雨の降る日は"},{"b":"傘","f":"かさ"},{"t":"さしても間に合うまいと思いやられるのもことわり、畳はすでに"},{"b":"苔","f":"こけ"},{"t":"むすばかりの有様であった。長虫は処を得て這いまわり、また翅虫は澱みを幸い湧きむらがって、人の"},{"b":"棲家","f":"すみか"},{"t":"とも思えなかった。さては和尚も苔むしたかと思われるほど、その逞しく巨大な姿は谷底に"},{"b":"崛起","f":"くっき"},{"t":"する岩石めき、まるまると盛りあがる額も頬も、垢にすすけて、黒々と岩肌の"},{"b":"光沢","f":"こうたく"},{"t":"を放つばかりであった。"}]},{"k":"p","r":[{"t":"　訪客は縁先ににじり寄った。"}]},{"k":"p","r":[{"t":"「もし、和尚さま」"}]},{"k":"p","r":[{"t":"　首を突き入れて、三たび、四たび繰返したが、声の通じた様子もなかった。"}]},{"k":"p","r":[{"t":"　たまりかねて、"},{"b":"濡縁","f":"ぬれえん"},{"t":"へ片膝をつき、這いこむばかりの姿勢となって、片腕を延して和尚の背中を揺ろうとした。"}]},{"k":"p","r":[{"t":"「もし、和尚さま」"}]},{"k":"p","r":[{"t":"　矢庭に彼はもんどり打って、土の上にころがっていた。彼はそのとき、今のさっき目に見たことが、如何様に工夫しても、呑みこみかねる有様であった。"}]},{"k":"p","r":[{"t":"　後向きの姿ではあるが、不興げな"},{"b":"翳","f":"かげ"},{"t":"が顔を"},{"b":"掠","f":"かす"},{"t":"めて走ったかと想像された一瞬間、たしかに和尚の姿がむくむくとふくれて、部屋いっぱいにひろがったのを認めた筈であったのである。"}]},{"k":"p","r":[{"t":"　腰骨の痛みも打忘れて、訪客は麓をさして逃げ帰った。"}]},{"k":"blank"},{"k":"p","r":[{"t":"　ある年、行暮れた旅人が、破れほうけた草庵を認めて立入り、旅寝の夢をむすんだ。"}]},{"k":"p","r":[{"t":"　すでに棲む人の姿はなく、壁は落ち、"},{"b":"羽目板","f":"はめいた"},{"t":"は外れて、夜風は身に沁みて吹き渡り、床の隙間に雑草がのびて、風吹くたびにその首をふった。"}]},{"k":"p","r":[{"t":"　"},{"b":"深更","f":"しんこう"},{"t":"、旅人はふとわが耳を疑りながら、目を覚した。その居る場所にすぐ近く、人々のざわめきの声がするのであった。それは遠くひろびろと笑いどよめく音にもきこえ、またすぐ近くあまたの人が声を殺して笑いさざめく音にもきこえた。"}]},{"k":"p","r":[{"t":"　旅人は音する方へにじり寄った。壁の孔を手探りにして、ひそかに覗いた。そうして、そこに、わが眼を疑る光景を見た。"}]},{"k":"p","r":[{"t":"　そこは広大な"},{"b":"伽藍","f":"がらん"},{"t":"であった。どのあたりから射してくる光とも分らないが、幽かに"},{"b":"漂","f":"ただよ"},{"t":"う明るさによっては、奥の深さ、天井の高さが、どの程度とも知りようがない。さて、広大な伽藍いっぱい、無数の小坊主が膝つき交えて"},{"b":"蠢","f":"うごめ"},{"t":"いていた。ひとりは人の袖をひき、ひとりはわが口を両手に抑え、ひとりは己れの頭をたたき、またひとりは"},{"b":"脾腹","f":"ひばら"},{"t":"を抑え、百態の限りをつくして、ののしり、笑いさざめいていた。"}]},{"k":"p","r":[{"t":"　やがて最も奥手の方に、ひとりの小坊主が立ち上った。左右の手に各小枝を握り、その両肩へ小枝を担う姿勢をとって、両肘を張り、一声高くこう歌った。"}]},{"k":"p","r":[{"t":"「花もなくて」"}]},{"k":"p","r":[{"t":"　歌いながら、へっぴり腰も面白く、飛立つように身も軽く一舞いした。"}]},{"k":"p","r":[{"t":"「あら"},{"b":"羞","f":"はずか"},{"t":"しや。羞しや」"}]},{"k":"p","r":[{"t":"　小坊主は節面白く歌いたてて、両手の小枝を高々と頭上に捧げ、きりきりと舞った。と、舞い終り、ひょいと尻を持上げて、一足ぽんと蹴りながら、放屁をもらした。"}]},{"k":"p","r":[{"t":"花もなくて。"}]},{"k":"p","r":[{"t":"あら羞しや。羞しや。"}]},{"k":"p","r":[{"t":"　小坊主は、舞い、歌い、放屁をたれ、こよなく悦に入ると見えた。同じ歌も、同じ舞いも、繰返すたびに調子づき、また屁の音も活気を帯びて、"},{"b":"賑","f":"にぎ"},{"t":"やかに速度をはやめた。"}]},{"k":"p","r":[{"t":"　放屁のたびに、"},{"b":"満座","f":"まんざ"},{"t":"の小坊主はどッとばかりにどよめいた。手をうつ者もあり、鼻をつまむ者もあり、耳に"},{"b":"蓋","f":"ふた"},{"t":"する者もあれば、さては矢庭にかたえの人の鼻をつまんで"},{"b":"捩","f":"ね"},{"t":"じあげる者もあった。ののしり、わめき、さて、ある者は逆立ちし、またある者は矢庭に人の股倉をくぐりぬければ、またある者はあおむけにでんぐり返って、両足をばたばた振った。"}]},{"k":"p","r":[{"t":"　異様なこととは言いながら、その可笑しさに堪えがたく、旅人は透見の身分も打忘れて、思わず笑声をもらした。"}]},{"k":"p","r":[{"t":"　どよめきは光と共に掻消え、あとは真の闇ばかり。ただ自らの笑声のみ妖しく耳にたつことを知ったとき、むんずと組みついた者のために、旅人はすんでに捩じ伏せられるところであった。必死の力でふりほどき、逃れようと"},{"b":"焦","f":"あせ"},{"t":"ってみたが、"},{"b":"絡","f":"から"},{"t":"みつく者は更に倍する怪力であった。精根つきはてて抵抗の気力を失ったとき、組みしかれた旅人は、毛だらけの脚が肩にまたがり、その両股に力をこめて、首をしめつけてくることを知った。"}]},{"k":"p","r":[{"t":"　ふと気がつけば、草庵の外に横たわり、露を受け、早朝の天日に"},{"b":"暴","f":"さら"},{"t":"されている自分の姿を見出した。"}]},{"k":"blank"},{"k":"p","r":[{"t":"　村人が寄り集い、草庵を"},{"b":"取毀","f":"とりこわ"},{"t":"したところ、仏壇の下に当った縁下に、大きな獣骨を発見した。片てのひらの白骨に朱の花の字がしみついていた。"}]},{"k":"p","r":[{"t":"　村人は"},{"b":"憐","f":"あわれ"},{"t":"んで塚を立て、周囲に数多の桜樹を植えた。これを花塚と称んだそうだが、春めぐり桜に花の開く毎に、塚のまわりの山々のみは嵐をよび、終夜悲しげに風声が叫びかわして、一夜に花を散らしたということである。この花塚がどのあたりやら、今は古老も知らないそうな。"}]},{"k":"p","r":[{"t":"（昭和13年『文体』２号）"}]}]}